{
  "lastUpdated": "2026-07-04T05:51:00.605Z",
  "articles": [
    {
      "title": "West Indies hope new ball brings change of luck after Udara bosses first day",
      "url": "https://www.cricinfo.com/ci/content/story/1544256.html?ex_cid=OTC-RSS",
      "description": "&quot;This is my third chance in Tests, so I thought I want to go big. I made it, so I'm really happy about that,&quot; Lahiru Udara says after scoring his first Test century",
      "publishedAt": "2026-07-04T05:14:58.000Z",
      "source": {
        "name": "ESPNcricinfo"
      },
      "urlToImage": null
    },
    {
      "title": "Lahiru Udara 188 carries the fight for Sri Lanka",
      "url": "https://www.cricinfo.com/ci/content/story/1544207.html?ex_cid=OTC-RSS",
      "description": "Record stand with Kamindu Mendis puts visitors in commanding position despite late West Indies strikes",
      "publishedAt": "2026-07-03T22:15:39.000Z",
      "source": {
        "name": "ESPNcricinfo"
      },
      "urlToImage": null
    },
    {
      "title": "Harmer and Cook help Essex hand out Hove thrashing",
      "url": "https://www.cricinfo.com/ci/content/story/1544238.html?ex_cid=OTC-RSS",
      "description": "Eagles captain hits 46 off 17 balls to boost total before claiming two wickets and effecting a run-out",
      "publishedAt": "2026-07-03T21:29:17.000Z",
      "source": {
        "name": "ESPNcricinfo"
      },
      "urlToImage": null
    },
    {
      "title": "Stone holds nerve as Notts seal one-run win to stay top",
      "url": "https://www.cricinfo.com/ci/content/story/1544236.html?ex_cid=OTC-RSS",
      "description": "Munsey continues hot streak with fifth half-century in six before Lancashire mess up run chase",
      "publishedAt": "2026-07-03T21:12:36.000Z",
      "source": {
        "name": "ESPNcricinfo"
      },
      "urlToImage": null
    },
    {
      "title": "Smale trail plots path for Glamorgan to win again",
      "url": "https://www.cricinfo.com/ci/content/story/1544235.html?ex_cid=OTC-RSS",
      "description": "Sam Hain hits 63 not out from 46 but Warwickshire unable to knock home side off course in chase",
      "publishedAt": "2026-07-03T21:02:06.000Z",
      "source": {
        "name": "ESPNcricinfo"
      },
      "urlToImage": null
    },
    {
      "title": "Bairstow, Moeen gun down Durham as Yorkshire close on knockouts",
      "url": "https://www.cricinfo.com/ci/content/story/1544237.html?ex_cid=OTC-RSS",
      "description": "Durham get off to flyer thanks to Alex Lees' 73 off 35 before stumbling, unable to defend 205-9",
      "publishedAt": "2026-07-03T20:49:03.000Z",
      "source": {
        "name": "ESPNcricinfo"
      },
      "urlToImage": null
    },
    {
      "title": "Johnson flattens Lancashire to keep Durham's Finals Day hopes alive",
      "url": "https://www.cricinfo.com/ci/content/story/1544217.html?ex_cid=OTC-RSS",
      "description": "Lancashire officially eliminated after sliding to 79 all out at Chester-le-Street",
      "publishedAt": "2026-07-03T20:21:25.000Z",
      "source": {
        "name": "ESPNcricinfo"
      },
      "urlToImage": null
    },
    {
      "title": "Hose, Raza get Rapids flowing before Kent collapse",
      "url": "https://www.cricinfo.com/ci/content/story/1544233.html?ex_cid=OTC-RSS",
      "description": "Visitors blown away for 59 with Allison, Raza and Mir all taking two apiece",
      "publishedAt": "2026-07-03T19:47:07.000Z",
      "source": {
        "name": "ESPNcricinfo"
      },
      "urlToImage": null
    },
    {
      "title": "Dawkins hundred, Flintoff 79* as England U19s level series",
      "url": "https://www.cricinfo.com/ci/content/story/1544231.html?ex_cid=OTC-RSS",
      "description": "Unbroken 191-run partnership sees South Africa comfortably overhauled",
      "publishedAt": "2026-07-03T19:43:55.000Z",
      "source": {
        "name": "ESPNcricinfo"
      },
      "urlToImage": null
    },
    {
      "title": "Winfield-Hill 99, Kalis 86* as Yorkshire romp to first Blast win",
      "url": "https://www.cricinfo.com/ci/content/story/1544215.html?ex_cid=OTC-RSS",
      "description": "Anika Learoyd's unbeaten hundred in vain as Somerset fall short in chase of 211",
      "publishedAt": "2026-07-03T17:08:32.000Z",
      "source": {
        "name": "ESPNcricinfo"
      },
      "urlToImage": null
    },
    {
      "title": "'That story is done' - Aakash Chopra picks his India playing XI for 2nd T20I between India and England",
      "url": "https://www.crictracker.com/cricket-news/that-story-is-done-aakash-chopra-picks-his-india-playing-xi-for-2nd-t20i-between-india-and-england/",
      "description": "Apart from picking India's playing XI for the second T20I against England, Aakash Chopra also suggested a change in the batting order from the last game.",
      "publishedAt": "2026-07-04T05:09:33.000Z",
      "source": {
        "name": "CricTracker"
      },
      "urlToImage": null
    },
    {
      "title": "'I don't want to put too much pressure' - Sam Curran on prospect of replacing Ben Stokes in England's Test side",
      "url": "https://www.crictracker.com/cricket-news/i-dont-want-to-put-too-much-pressure-sam-curran-on-prospect-of-replacing-ben-stokes-in-englands-test-side/",
      "description": "The Surrey all-rounder stated that he would happily take over the vacant spot left behind by Stokes if asked to do so",
      "publishedAt": "2026-07-04T04:37:13.000Z",
      "source": {
        "name": "CricTracker"
      },
      "urlToImage": null
    },
    {
      "title": "'Family, friends, teammates, fans…' - Ben Stokes pens emotional farewell message after retiring from international cricket",
      "url": "https://www.crictracker.com/cricket-news/family-friends-teammates-fans-ben-stokes-pens-emotional-farewell-message-after-retiring-from-international-cricket/",
      "description": "Stokes brought the curtain down on an illustrious international career during the third Test against New Zealand at Trent Bridge.",
      "publishedAt": "2026-07-03T17:01:52.000Z",
      "source": {
        "name": "CricTracker"
      },
      "urlToImage": null
    },
    {
      "title": "ENG vs IND, 2nd T20I: England announces playing XI as Jofra Archer returns, Josh Tongue handed T20I debut",
      "url": "https://www.crictracker.com/cricket-news/eng-vs-ind-2nd-t20i-england-announces-playing-xi-as-jofra-archer-returns-josh-tongue-handed-t20i-debut/",
      "description": "The duo replaces Saqib Mahmood and Luke Wood, who featured in the rain-affected series opener.",
      "publishedAt": "2026-07-03T16:25:07.000Z",
      "source": {
        "name": "CricTracker"
      },
      "urlToImage": null
    },
    {
      "title": "England hand maiden ODI call-up to James Coles; Jofra Archer returns for India series",
      "url": "https://www.crictracker.com/cricket-news/england-hand-maiden-odi-call-up-to-james-coles-jofra-archer-returns-for-india-series/",
      "description": "Archer returns to England's ODI setup for the first time since featuring against the West Indies in November last year.",
      "publishedAt": "2026-07-03T14:38:46.000Z",
      "source": {
        "name": "CricTracker"
      },
      "urlToImage": null
    },
    {
      "title": "'How he handles that will be his biggest challenge' - Sam Curran sounds caution for Vaibhav Sooryavanshi ahead of ENG vs IND 2nd T20I",
      "url": "https://www.crictracker.com/cricket-news/sam-curran-sounds-caution-for-vaibhav-sooryavanshi-ahead-of-2nd-t20i/",
      "description": "Sam Curran highlighted some of the challenges that Vaibhav Sooryavanshi might face if he finally gets to make his India debut at the age of 15.",
      "publishedAt": "2026-07-03T13:21:56.000Z",
      "source": {
        "name": "CricTracker"
      },
      "urlToImage": null
    },
    {
      "title": "England vs India Prediction, 2nd T20I – Who will win today’s match between ENG vs IND?",
      "url": "https://www.crictracker.com/cricket-match-predictions/england-vs-india-prediction-2nd-t20i-who-will-win-todays-match-between-eng-vs-ind/",
      "description": "England and India square off in the second T20I at Old Trafford, Manchester, on Saturday, July 4. The series is tied at 0-0, with the first game being washed out in Chester-le-Street on Wednesday.",
      "publishedAt": "2026-07-03T12:51:23.000Z",
      "source": {
        "name": "CricTracker"
      },
      "urlToImage": null
    },
    {
      "title": "BBL set for historic India debut as Melbourne Renegades and Perth Scorchers likely to face off in Chennai",
      "url": "https://www.crictracker.com/cricket-news/null/",
      "description": "The proposal is in its final stages and is subject to a formal agreement between Cricket Australia and the Asian Cricket Council.",
      "publishedAt": "2026-07-03T11:27:24.000Z",
      "source": {
        "name": "CricTracker"
      },
      "urlToImage": null
    },
    {
      "title": "ENG vs IND 2026: 'Will definitely get an opportunity' - Parthiv Patel on Vaibhav Sooryavanshi's non-selection",
      "url": "https://www.crictracker.com/cricket-news/eng-vs-ind-2026-will-definitely-get-an-opportunity-parthiv-patel-on-vaibhav-sooryavanshis-non-selection/",
      "description": "Clamours for his debut have become increasingly fervent, but Sooryavanshi has yet to feature in the two T20Is against Ireland and one against England.",
      "publishedAt": "2026-07-03T09:42:46.000Z",
      "source": {
        "name": "CricTracker"
      },
      "urlToImage": null
    },
    {
      "title": "'Sanju Samson hasn’t done anything great since the World Cup' - S Badrinath’s brutal claim on Team India star ahead of 2nd T20I vs England",
      "url": "https://www.crictracker.com/cricket-news/sanju-samson-hasnt-done-anything-great-since-the-world-cup-s-badrinaths-brutal-claim-on-team-india-star-ahead-of-2nd-t20i-vs-england/",
      "description": "\"Timing is very important for a player in form. He should be given a chance when he is in the form of his life,\" Subramaniam Badrinath said about Vaibhav Sooryavanshi.",
      "publishedAt": "2026-07-03T10:51:52.000Z",
      "source": {
        "name": "CricTracker"
      },
      "urlToImage": null
    },
    {
      "title": "'They're best team by a mile': Pakistan coach calls out India obsession in judging his team - The Times of India",
      "url": "https://news.google.com/rss/articles/CBMi_gFBVV95cUxPOXk5a1pyWjVUdnduTEgyV05tTURzYlFPY3lEa1FWb18zVmNKQ0NLS0pJZ2ZfNkdIZ2lDNHRGaHVKaW1BYzQ2WEFoblVXOEQ2OFVoS1k4ZU9fU3EyTkdaZWdmRW40Wm1kTnJwUmhtT2xuclRKS0dCM0hWcUpSTjdUd1Rsc0tNbG5YbUtiQkNRcGdBNXBfZWhTVmo1eHJiMHMwaUVOaHBjX0FDeWVjMjV4QzFVLThlUjBkSEJvWnc3QnJJQVJFbzVpX0R1NGNYRmpOVmFsQ0x4aFVxS0lIZXkxeUpHLXZIYUMxT1hndUxfa25ORnFBbDRaLUwwdk1vd9IBgwJBVV95cUxOWGF0SzZxZmxhaU5uSXh5TlVEUi1QOXItaWtuVXNRdmNmNTZrUWpYQmlFNi1mV1dFcTFwREk3eFJENVZyY3VzVjc2WTF4bDFKbmF3dmEtd2U1WE1sNzRMOHRaRFpaRkd2b3JlOWRuNW5pcFhZMTdMeUNiVlJtdXN3S2dvcGItWFBvUGI5Z3RGTGtaVC1Hb0d5WmR1VzVsVzZFV1RMMkl6VjRxWHdWOUttaUxKclFWZnVYTldocUFZc3hiZmk5MVh5TXFjS09iR0kwOF9xbUwzYkc5OVRqclBZeXdCb3paQ1JwVGNYeGpTdW9ud1pwWktRREpET0tUaENUdTZr?oc=5",
      "description": "<a href=\"https://news.google.com/rss/articles/CBMi_gFBVV95cUxPOXk5a1pyWjVUdnduTEgyV05tTURzYlFPY3lEa1FWb18zVmNKQ0NLS0pJZ2ZfNkdIZ2lDNHRGaHVKaW1BYzQ2WEFoblVXOEQ2OFVoS1k4ZU9fU3EyTkdaZWdmRW40Wm1kTnJwUmhtT2xuclRKS0dCM0hWcUpSTjdUd1Rsc0tNbG5YbUtiQkNRcGdBNXBfZWhTVmo1eHJiMHMwaUVOaHBjX0FDeWVjMjV4QzFVLThlUjBkSE",
      "publishedAt": "2026-07-03T10:26:00.000Z",
      "source": {
        "name": "Google News"
      },
      "urlToImage": null
    },
    {
      "title": "Nat Sciver-Brunt - Wicket - England vs South Africa - ICC",
      "url": "https://news.google.com/rss/articles/CBMiuwFBVV95cUxPLTd2cTAxMkhwaXFKMi1FUXB5QlZhMUFVU3dqVEVZRGRQSUxYMXlQVHYtbGdRMUVVbXZQd0VSSTdHV0NEek5UME5NLWs1UXZBZ092cFhtbHZRdDJjLXk2OFNrbEJYV2pPVURKRnYtQm1OR0Z5ZFhuTWxkdkxuN0QzQlltbjRLbE95Qy1uM2Z0bzVnMUxyNzJSeWVlc1BKN3N6UmIxbDJsOGJpTHhlNEFBelFkcG5EVmF5SWl3?oc=5",
      "description": "<a href=\"https://news.google.com/rss/articles/CBMiuwFBVV95cUxPLTd2cTAxMkhwaXFKMi1FUXB5QlZhMUFVU3dqVEVZRGRQSUxYMXlQVHYtbGdRMUVVbXZQd0VSSTdHV0NEek5UME5NLWs1UXZBZ092cFhtbHZRdDJjLXk2OFNrbEJYV2pPVURKRnYtQm1OR0Z5ZFhuTWxkdkxuN0QzQlltbjRLbE95Qy1uM2Z0bzVnMUxyNzJSeWVlc1BKN3N6UmIxbDJsOGJpTHhlNEFBelFkcG5EVmF5SW",
      "publishedAt": "2026-07-02T19:06:41.000Z",
      "source": {
        "name": "Google News"
      },
      "urlToImage": null
    },
    {
      "title": "Women’s T20 World Cup 2026: Tazmin Brits hopes to make LA 2028 Olympics squad for South Africa - Sportstar",
      "url": "https://news.google.com/rss/articles/CBMi8wFBVV95cUxQYy00blVpUmdwRDJVX2NMX0JpVlJrNXVEUFJRUTRWbFk4U1NkZGNBTUJaVVl0U1Q2RE1Gb0Q5Y185NmJud253bFhJU0txMkdjMnVQdVI5Tm5McFZWT1RaM3FwaU1TRERreEF6elhodDBJT280UHhFTTRHV25jb2Rxek52eVc2YnlGQWR3bGYtZ2VmWWdJUTZ2N2gwa3RkaFBRTjQyV1ZSQUc3NnE2alZtbnRERVV0bk5reVVKM19uTDZSR1BDWnFMSTZSS1BkY2pOQkNERmVzVzJSWGFzd1lrcUtMRmN2LVlVY1kzOFlQZ3hMbGPSAfoBQVVfeXFMUExWNU5jdWx3eWlNSlZlRHJrcTVUTlJTMzgtNDR5OXhpR0MyVVNBY2wyNFkxZGl3NDY5V2tKSjVsbmtiZDNPYVNsMzZ2cS1TVUtKc0pxRTh2bWNfc2tuZnNMVEtiZEx0LWhUQzkzQmM4anJhUzEzM0oxOHhqS0tqSGZxZUdKVm1JbXlINVRKVnhuYTVTZzB0WlNSekFJVVRUZlN2QzBZUVQyamlESVp5Vkd0Q3lpLU1TdWN0Z1JUbU1kQXpkR0hYS3pEN25sa2U5UUhTTnZzdU04eFR5X3JSZUlRYmFzanN4eTVkaUMwaHJEbjNGLTlYbkY1QQ?oc=5",
      "description": "<a href=\"https://news.google.com/rss/articles/CBMi8wFBVV95cUxQYy00blVpUmdwRDJVX2NMX0JpVlJrNXVEUFJRUTRWbFk4U1NkZGNBTUJaVVl0U1Q2RE1Gb0Q5Y185NmJud253bFhJU0txMkdjMnVQdVI5Tm5McFZWT1RaM3FwaU1TRERreEF6elhodDBJT280UHhFTTRHV25jb2Rxek52eVc2YnlGQWR3bGYtZ2VmWWdJUTZ2N2gwa3RkaFBRTjQyV1ZSQUc3NnE2alZtbnRERVV0bk5reV",
      "publishedAt": "2026-07-03T15:18:17.000Z",
      "source": {
        "name": "Google News"
      },
      "urlToImage": null
    },
    {
      "title": "Rita Ora To Headline ICC Women's T20 World Cup 2026 Final; Clean Bandit To Perform After Match - News18",
      "url": "https://news.google.com/rss/articles/CBMi5gFBVV95cUxPelRtdUVjWGdVX2hjMGpDY0RTeVAtZ191anA0WTdYYkV2cThVaVNZRGdBRTNfelM1YXFaX1NPTnlkSy1tOUtKdm85bGxVclUtUE9KQi1KUERlQktkY0NBTkpONU14Yi1aZHVKWXFUaE5sdk9kSlFfbXlvcExPdDhRRVJyYl9UM3E3VXdjQlgwdnljRVMwYnV5MVlLdG11WHhpWHJsZ1AySnR3c18xdXZsNUwwN0o3bUhONTZXMmlYVnROZXhVbFdmZXE3Z01wMGtvUHRHeGo1bFhfZlFFSWdPTXlpaTN0Z9IB6wFBVV95cUxQZ0lIcDhWeDU3RXhXd1lkdTJqdzh2bTNJZ0lqSTlTVGFpTTVaTUN0ZlFEY25Pc3NmYTkzdWNoYTA2SWhiMU1nNDNLRlNBNjJIU18xR3JLMnNuaUlsQlFFMm9mXzNyalc0WUtSNkdCdExBWFBXbkRJamg3aTlFdng2dTNCbW1td1NhM3JuamZlejNRcVE5OVQxaWxmUlJsV0xnWHdsR3d5UTZKVURGQXFjNWdBMV82SHJqTktSSDBmS291VHN4TXlqdDJFSkR4YzFuVTZHNmFNc0VUTFhqd0s4QVRyMWVvQXNjSy1J?oc=5",
      "description": "<a href=\"https://news.google.com/rss/articles/CBMi5gFBVV95cUxPelRtdUVjWGdVX2hjMGpDY0RTeVAtZ191anA0WTdYYkV2cThVaVNZRGdBRTNfelM1YXFaX1NPTnlkSy1tOUtKdm85bGxVclUtUE9KQi1KUERlQktkY0NBTkpONU14Yi1aZHVKWXFUaE5sdk9kSlFfbXlvcExPdDhRRVJyYl9UM3E3VXdjQlgwdnljRVMwYnV5MVlLdG11WHhpWHJsZ1AySnR3c18xdXZsNUwwN0o3bUhONT",
      "publishedAt": "2026-07-03T06:12:01.000Z",
      "source": {
        "name": "Google News"
      },
      "urlToImage": null
    },
    {
      "title": "Women’s T20 World Cup 2026: Dean says Australia final a ‘fresh start’ for England - Sportstar",
      "url": "https://news.google.com/rss/articles/CBMioAJBVV95cUxOaHEteGhodElQR05mLTB3UTZIaS1lYU1ZYk5YNU9mcTJZMThyQ2ZyN1BtQzMyTlE4Ry1hOGxXLXByRUhad0hYRk9lbTZnd1otZ0FONmZjV2NWdHNodzFsOXZEWUdHaUZlajhHNmh5akRsSnF1emdubDhtQjBSRGdDQXRKamlIS3NFV0FudDltOS1OWnp0YU94dWw1emwxN1M2dlRUTkxBaDg4UktlWGRNS25zNWJrZHdfQTcyTEJFTGg5UzhzM21zRjcxYnQxeEJiVWVXQ3lHUDFnU091ZlROQVNPZGxsa2E0T0NnVVEyYlIyaGhMVnZwQ2xvZ1BtbExOT0RXM25NeGFBTXloWTAyLVB2dTZTcWRXdjQ4X2c5Rk3SAacCQVVfeXFMT3hfSUZVaVJ2RktjaldSdnU1NjE2ekJ4TUdOZ1FLY21XMU5hTHNXc0J5SThBUW9OYy01c2lCaGxRVGZxUEdiSFF6UEprXzFoMTBCVGxMYVZNeXpQRkJGQWZJOEI1NlZod25aR2hXZTVtYWR4ajJSa1NrLW5tNlFaTG5hV0daYkxDblZSTkJZWUdkOEV1Zm1tcUdwWEd6TWtHeWpGNXJIRFZfdVFRYUY2MEljdHNkck5hR3F3TDZ4YXMzZF9WeThLckxyNWNaQnRxVm55WDgzZU9ZazJSMkVZdUhYd0p5YlVseG1iUTZ2VHBJckhLNmZWSU5hUGZWbGhvaklTWTA1T2MtNm85bzI4YmhCOEpqQkY2bnI2TDRaVmJFb0VRdzlFcw?oc=5",
      "description": "<a href=\"https://news.google.com/rss/articles/CBMioAJBVV95cUxOaHEteGhodElQR05mLTB3UTZIaS1lYU1ZYk5YNU9mcTJZMThyQ2ZyN1BtQzMyTlE4Ry1hOGxXLXByRUhad0hYRk9lbTZnd1otZ0FONmZjV2NWdHNodzFsOXZEWUdHaUZlajhHNmh5akRsSnF1emdubDhtQjBSRGdDQXRKamlIS3NFV0FudDltOS1OWnp0YU94dWw1emwxN1M2dlRUTkxBaDg4UktlWGRNS25zNWJrZHdfQT",
      "publishedAt": "2026-07-03T12:05:45.000Z",
      "source": {
        "name": "Google News"
      },
      "urlToImage": null
    },
    {
      "title": "T20 World Cup: Charlie Dean's journey from Lord's tears to England's stand-in captain - BBC",
      "url": "https://news.google.com/rss/articles/CBMiZkFVX3lxTE1SNmRwekNDMUR5UFFQVl9DZnFEWURvWWR5bEU3OFN2YzJYUU1Xb1M5ZmEzVWRFUnJHclNxRzRWUU5CdDlFV1R2YWhzTFJqYVpKY2FhaUp5OW85WEs3TU9MWmdxLVpkQQ?oc=5",
      "description": "<a href=\"https://news.google.com/rss/articles/CBMiZkFVX3lxTE1SNmRwekNDMUR5UFFQVl9DZnFEWURvWWR5bEU3OFN2YzJYUU1Xb1M5ZmEzVWRFUnJHclNxRzRWUU5CdDlFV1R2YWhzTFJqYVpKY2FhaUp5OW85WEs3TU9MWmdxLVpkQQ?oc=5\" target=\"_blank\">T20 World Cup: Charlie Dean's journey from Lord's tears to England's stand-in captain</a>",
      "publishedAt": "2026-07-02T05:19:53.000Z",
      "source": {
        "name": "Google News"
      },
      "urlToImage": null
    },
    {
      "title": "Melbourne Renegades vs Perth Scorchers in Chennai: Cricket Australia finalises BBL 2026 opener as Big Bash comes to India - Yahoo Sports",
      "url": "https://news.google.com/rss/articles/CBMikAFBVV95cUxORWItTy1MeC1nb2JTc21Fd2ctb2xLMElsOWJManZzUUVhRjg0QllfMW5OSVNHZlNwcnMwTFc0aXk2TW1BYmZEXzAwdkJNZXJkcDBmUzJNSTBoUWdrTkdMcFJlNFdoYnNaOC1UMXR1NkdwTjZCZDRJVFRndkNUMklJc1BFTzhmdGs2MzYtaXhXcVo?oc=5",
      "description": "<a href=\"https://news.google.com/rss/articles/CBMikAFBVV95cUxORWItTy1MeC1nb2JTc21Fd2ctb2xLMElsOWJManZzUUVhRjg0QllfMW5OSVNHZlNwcnMwTFc0aXk2TW1BYmZEXzAwdkJNZXJkcDBmUzJNSTBoUWdrTkdMcFJlNFdoYnNaOC1UMXR1NkdwTjZCZDRJVFRndkNUMklJc1BFTzhmdGs2MzYtaXhXcVo?oc=5\" target=\"_blank\">Melbourne Renegades vs Perth Sco",
      "publishedAt": "2026-07-03T08:25:36.000Z",
      "source": {
        "name": "Google News"
      },
      "urlToImage": null
    },
    {
      "title": "REVEALED: Historic first for Big Bash opener as fixture released - Fox Sports",
      "url": "https://news.google.com/rss/articles/CBMilgJBVV95cUxPb0k1bzFLZWlRX3FfUzRXb293NkFTYkZYSURrZG80WkJ5R0RRLUVEdkM4bkdnT3lyWVlSRkhDbUNUR3RFSjhMc21aNUhwTjJYM3dibFVIaUE5Tmg0Y3ZMZm5vUGdCR21lVzNWLVlQMDhCZ1lZdjhMY29LakIyRnpMYmJZWmxMUmhyWnBab0NPUWd5bnV5UFBtVEM0QlNONjJVQUdxLWxTUzRrX1pwbWYwSWp0cEM0R2xJYm9FcjRTOEtJQzBzS1JaTGxfRVhyNTRmOGtMQktlVFI1ZF9BYV8tbWxLS2RQY294QS1PRHdwTWJxeUFfdW0wQ3hYUFJjLVV1T01PUS1QTTlGYkZWVXlkUG9ic05IQdIBlgJBVV95cUxPb0k1bzFLZWlRX3FfUzRXb293NkFTYkZYSURrZG80WkJ5R0RRLUVEdkM4bkdnT3lyWVlSRkhDbUNUR3RFSjhMc21aNUhwTjJYM3dibFVIaUE5Tmg0Y3ZMZm5vUGdCR21lVzNWLVlQMDhCZ1lZdjhMY29LakIyRnpMYmJZWmxMUmhyWnBab0NPUWd5bnV5UFBtVEM0QlNONjJVQUdxLWxTUzRrX1pwbWYwSWp0cEM0R2xJYm9FcjRTOEtJQzBzS1JaTGxfRVhyNTRmOGtMQktlVFI1ZF9BYV8tbWxLS2RQY294QS1PRHdwTWJxeUFfdW0wQ3hYUFJjLVV1T01PUS1QTTlGYkZWVXlkUG9ic05IQQ?oc=5",
      "description": "<a href=\"https://news.google.com/rss/articles/CBMilgJBVV95cUxPb0k1bzFLZWlRX3FfUzRXb293NkFTYkZYSURrZG80WkJ5R0RRLUVEdkM4bkdnT3lyWVlSRkhDbUNUR3RFSjhMc21aNUhwTjJYM3dibFVIaUE5Tmg0Y3ZMZm5vUGdCR21lVzNWLVlQMDhCZ1lZdjhMY29LakIyRnpMYmJZWmxMUmhyWnBab0NPUWd5bnV5UFBtVEM0QlNONjJVQUdxLWxTUzRrX1pwbWYwSWp0cEM0R2xJYm",
      "publishedAt": "2026-07-02T06:00:22.000Z",
      "source": {
        "name": "Google News"
      },
      "urlToImage": null
    },
    {
      "title": "Why is Big Bash League coming to India? Chennai to host BBL 2026-27 opener - sportingnews.com",
      "url": "https://news.google.com/rss/articles/CBMixgFBVV95cUxOcTlRdWg2VW43RS1jd1VReEpfMmFzTUxsSWlfWm0ydmw5aVZOdW8ycjVWSlNLM2ExOGhlR1JjcGVWbWF4bWlTd0I3RndGNTNWdkpCb2J1SmtIc0VHOHlLdVBFMTVvQ3UySXlma2RZd2YtYXdEWG84alYxdThxU3FPRFFGY2NPZkU5NDd1WTNPQ3N5N0k3OHg0SnhOQjFyMjVDdUppd0VNQ1VwZjJMV1YtenhPeVpjOFlXZTlkc1Nna1dlSlRwOXc?oc=5",
      "description": "<a href=\"https://news.google.com/rss/articles/CBMixgFBVV95cUxOcTlRdWg2VW43RS1jd1VReEpfMmFzTUxsSWlfWm0ydmw5aVZOdW8ycjVWSlNLM2ExOGhlR1JjcGVWbWF4bWlTd0I3RndGNTNWdkpCb2J1SmtIc0VHOHlLdVBFMTVvQ3UySXlma2RZd2YtYXdEWG84alYxdThxU3FPRFFGY2NPZkU5NDd1WTNPQ3N5N0k3OHg0SnhOQjFyMjVDdUppd0VNQ1VwZjJMV1YtenhPeVpjOFlXZT",
      "publishedAt": "2026-07-03T07:50:19.000Z",
      "source": {
        "name": "Google News"
      },
      "urlToImage": null
    },
    {
      "title": "‘Alive again’: Major BBL reveal as club left in awkward state of limbo before massive Draft call - Fox Sports",
      "url": "https://news.google.com/rss/articles/CBMitgJBVV95cUxQajM0c0FGTDZ6cEtDZS1TRDlLaWxkbVhNZDFFLW05Tld3OVRUeE1SdmFJOTFXVWo0azRrb3lZRXh0MWViem1zME8yajA1UlJjdXZhMjlULXFCanIzS1lES0NfM0d5b21RU2c2dVNqcjdmVHYzS194YnRZOEpGUjNWOFhVa1MtM3ROc2xjN094NlNsenVzNWZqSGxUMWlsZ09oc0xQbjVDUjJBTGZQa1FKMWJRc3doZjB2dUYzaGkzY1hVU1ZBVFQ3elp0eFQtRmdvVGlvQmRUN3FTWV8xUVh2WXl0cmtCZU4yanQteTFGNkJJcVE0N04zamVGX2dfVGttbFFNQnBmOTUzMjcteGxpLUNOaWNRV2JPUVlYOFJHNncxU21rbEN3OGl4R2tCeGFBWEx0YjNB0gG2AkFVX3lxTFBqMzRzQUZMNnpwS0NlLVNEOUtpbGRtWE1kMUUtbTlOV3c5VFR4TVJ2YUk5MVdVajRrNGtveVlFeHQxZWJ6bXMwTzJqMDVSUmN1dmEyOVQtcUJqcjNLWURLQ18zR3lvbVFTZzZ1U2pyN2ZUdjNLX3hidFk4SkZSM1Y4WFVrUy0zdE5zbGM3T3g2U2x6dXM1ZmpIbFQxaWxnT2hzTFBuNUNSMkFMZlBrUUoxYlFzd2hmMHZ1RjNoaTNjWFVTVkFUVDd6WnR4VC1GZ29UaW9CZFQ3cVNZXzFRWHZZeXRya0JlTjJqdC15MUY2QklxUTQ3TjNqZUZfZ19Ua21sUU1CcGY5NTMyNy14bGktQ05pY1FXYk9RWVg4Ukc2dzFTbWtsQ3c4aXhHa0J4YUFYTHRiM0E?oc=5",
      "description": "<a href=\"https://news.google.com/rss/articles/CBMitgJBVV95cUxQajM0c0FGTDZ6cEtDZS1TRDlLaWxkbVhNZDFFLW05Tld3OVRUeE1SdmFJOTFXVWo0azRrb3lZRXh0MWViem1zME8yajA1UlJjdXZhMjlULXFCanIzS1lES0NfM0d5b21RU2c2dVNqcjdmVHYzS194YnRZOEpGUjNWOFhVa1MtM3ROc2xjN094NlNsenVzNWZqSGxUMWlsZ09oc0xQbjVDUjJBTGZQa1FKMWJRc3doZjB2dU",
      "publishedAt": "2026-07-02T06:03:45.000Z",
      "source": {
        "name": "Google News"
      },
      "urlToImage": null
    },
    {
      "title": "Ben Stokes says his final goodbye to international cricket? Details inside - MSN",
      "url": "https://news.google.com/rss/articles/CBMihAJBVV95cUxNLXoyQ1R2aUV0SFVMdmlpVlBGdU04TzVTYU55cXBaaVZhSE9LV3cyTzJGcm5jcFVtSmVzcnYwVk1pMTZpN2hrdW9EaGF4SnZzeXA3eVd1ZXlhYzhXaVlrSzhzOTBwbERWV0p4dkh6LTN6RlZSZkR1NEYwYWpUcE56cGtpVzJzV2RTcjRfcHFsdGFSczZQbGtFQjB5bXpObmtrdXc1RDNHcUdVT0FiWXBMTEhtNDhLeDJsRWVWTWVrZXRqdy11RXJWWDVuczU4SHF2X3FmS1FCSWxLUVM4M1Z0c3NQY3JyNXIwQkI2U3l0VHFpakF4eXItZ2hXc256QWdhWTJ5aA?oc=5",
      "description": "<a href=\"https://news.google.com/rss/articles/CBMihAJBVV95cUxNLXoyQ1R2aUV0SFVMdmlpVlBGdU04TzVTYU55cXBaaVZhSE9LV3cyTzJGcm5jcFVtSmVzcnYwVk1pMTZpN2hrdW9EaGF4SnZzeXA3eVd1ZXlhYzhXaVlrSzhzOTBwbERWV0p4dkh6LTN6RlZSZkR1NEYwYWpUcE56cGtpVzJzV2RTcjRfcHFsdGFSczZQbGtFQjB5bXpObmtrdXc1RDNHcUdVT0FiWXBMTEhtNDhLeDJsRW",
      "publishedAt": "2026-07-02T19:00:55.000Z",
      "source": {
        "name": "Google News"
      },
      "urlToImage": null
    },
    {
      "title": "Ben Stokes gives emotional speech after announcing his retirement from international cricket - ESPN Philippines",
      "url": "https://news.google.com/rss/articles/CBMivwFBVV95cUxQOTZOOTEtc0czNmtfUVQ5SWd3eTVKSGtkUHhISFdYSVBNaHJfa2FXZWlpeTlYeG1CdlUzQWxKNU40dlVtamVWY2JWM3M0Mk0yZ1NQWllhYlFubjhSZ1JnQmdTWVp4RWVTOGYxMWtCZVgzUkNsN1p3M0Q1TDFrNjAtcnh6MmpoVkdJbEVieDVqTjVyMjkyZEdtRHlZYlNaTGREVUZ5bEZaTHBaVWpWMFhocjgtQzVhc1hrcVZMOUxaaw?oc=5",
      "description": "<a href=\"https://news.google.com/rss/articles/CBMivwFBVV95cUxQOTZOOTEtc0czNmtfUVQ5SWd3eTVKSGtkUHhISFdYSVBNaHJfa2FXZWlpeTlYeG1CdlUzQWxKNU40dlVtamVWY2JWM3M0Mk0yZ1NQWllhYlFubjhSZ1JnQmdTWVp4RWVTOGYxMWtCZVgzUkNsN1p3M0Q1TDFrNjAtcnh6MmpoVkdJbEVieDVqTjVyMjkyZEdtRHlZYlNaTGREVUZ5bEZaTHBaVWpWMFhocjgtQzVhc1hrcV",
      "publishedAt": "2026-06-28T16:08:16.000Z",
      "source": {
        "name": "Google News"
      },
      "urlToImage": null
    },
    {
      "title": "Stokes’ theatrical retirement has left England cricket in a mess. That might have been the intention - SMH.com.au",
      "url": "https://news.google.com/rss/articles/CBMiuAFBVV95cUxPYnhxU0g4ajYzYjBnWjJ4R3FRTW5ROXVnSmNmM1Q3NllWRm5uQmttNjVaSGdNakp1Nm1DcTBydmJMNWp5Wm91OFRPSGhBVFRFdHF4ZkZkNVh6WnJXQzNIME9JTTZHY29wbmhvYVNmZi1rbFk3SGhfZHUyV3hfd0M1MlhXeFJIQ25GVTBrLWZsN25DaXA5N1p5cXdTdzI4ZGtSb2wxblc5cy1IVThrQnlIZnhvTDVMSzZ6?oc=5",
      "description": "<a href=\"https://news.google.com/rss/articles/CBMiuAFBVV95cUxPYnhxU0g4ajYzYjBnWjJ4R3FRTW5ROXVnSmNmM1Q3NllWRm5uQmttNjVaSGdNakp1Nm1DcTBydmJMNWp5Wm91OFRPSGhBVFRFdHF4ZkZkNVh6WnJXQzNIME9JTTZHY29wbmhvYVNmZi1rbFk3SGhfZHUyV3hfd0M1MlhXeFJIQ25GVTBrLWZsN25DaXA5N1p5cXdTdzI4ZGtSb2wxblc5cy1IVThrQnlIZnhvTDVMSzZ6?o",
      "publishedAt": "2026-06-29T01:19:31.000Z",
      "source": {
        "name": "Google News"
      },
      "urlToImage": null
    },
    {
      "title": "Ben Stokes explains stunning England retirement: ‘I don’t think I have any fight left in me’ - The Independent",
      "url": "https://news.google.com/rss/articles/CBMirgFBVV95cUxOOWZZNUpaSjBNN2k3UzRrcW1PNXkwSjNfQU5oVXRTalBCakZYVTJEd295Z0ZQRlRjVlZuWU1kZXE0STlSQzYxbkJXM214c1AyWFhScUF1WjFKb0JaWVhCVEgyQ0lTVVJwbVd2U0lscExRMGt3Wm1rLS1OWnljb283a0ZveXBFaHBsQWNmMGR5U2JoQnNDc0VNTEFENWdGQkZVTmRhbF91emRxMTVzdnc?oc=5",
      "description": "<a href=\"https://news.google.com/rss/articles/CBMirgFBVV95cUxOOWZZNUpaSjBNN2k3UzRrcW1PNXkwSjNfQU5oVXRTalBCakZYVTJEd295Z0ZQRlRjVlZuWU1kZXE0STlSQzYxbkJXM214c1AyWFhScUF1WjFKb0JaWVhCVEgyQ0lTVVJwbVd2U0lscExRMGt3Wm1rLS1OWnljb283a0ZveXBFaHBsQWNmMGR5U2JoQnNDc0VNTEFENWdGQkZVTmRhbF91emRxMTVzdnc?oc=5\" target=\"",
      "publishedAt": "2026-06-28T18:53:00.000Z",
      "source": {
        "name": "Google News"
      },
      "urlToImage": null
    },
    {
      "title": "England turn on Stokes after ‘insulting’ act - News.com.au",
      "url": "https://news.google.com/rss/articles/CBMikgJBVV95cUxPbzZSaHptSE9lNEFBYjVGV3lBU1VnMEpHSnFOQ1Q2NldYNEcyZjdtbExjT0pxZm84SHJ6WHU1NklCVXhZOUdhQmNjODZGcnQ5RW9xVXIwd3FoSDB1TDhWNDdPWUliTkNMS3hoX2YwYzQ1QUFsQ1dHQ0U2aHpjS05Pa0Q0UWUyYTBvamRHVUpMLUJZMExwcFlDN1dvMjYtU1NKV3RyTWp0Q3ZhbFhXRUkycS1heGh5U0pCakpWSWJpT240QVlPaG16RW5Pb3NiWVNXemNwbE1QXzVIM2d2bWZzTUh1ZVBRcEZtS2tESlN5Q2RKSXVtbksxeG00TEN5TUtHREJWZWNtNDJaNzRvTGR3N0RB0gGXAkFVX3lxTFBMekkxcUZJcTJOS1dJcEZENm9mdmZjUU5qT0NtVXBtVktHSlZzYmVSYXJCNUpYUktWSjd6d1lhMXBlc1dnc1ltcWxPQTJlVm5teHl5TEw3bUpjX2RKMmtHV1ZVUXZoZEVzeEdnLXhsY1VmbXBELWx5UTY0ZEtuTUYzYW5YSXFYdzJLWEhuLU95WnhPM0tWOVBnZHJwWkktVUEtT0hIWjFjMFR5VC16T3ZJbjNuaGtzV2djR3h3bEE5OHBMOWNvT0ZsdmtfSUt2ZHNLU0Zra0lLNmRfYkZzZk56TmpjaXNGeVkwaVlueTJHb0owLXA1X29xcmJjc1NLd1VqbC15Vi1zTFo5TnJReWxNMmtyWDRTYw?oc=5",
      "description": "<a href=\"https://news.google.com/rss/articles/CBMikgJBVV95cUxPbzZSaHptSE9lNEFBYjVGV3lBU1VnMEpHSnFOQ1Q2NldYNEcyZjdtbExjT0pxZm84SHJ6WHU1NklCVXhZOUdhQmNjODZGcnQ5RW9xVXIwd3FoSDB1TDhWNDdPWUliTkNMS3hoX2YwYzQ1QUFsQ1dHQ0U2aHpjS05Pa0Q0UWUyYTBvamRHVUpMLUJZMExwcFlDN1dvMjYtU1NKV3RyTWp0Q3ZhbFhXRUkycS1heGh5U0pCak",
      "publishedAt": "2026-06-29T05:18:14.000Z",
      "source": {
        "name": "Google News"
      },
      "urlToImage": null
    },
    {
      "title": "Ben Stokes says his final goodbye to international cricket? Details inside - MSN",
      "url": "https://news.google.com/rss/articles/CBMihAJBVV95cUxQNllldmI5Zzc4SEdKc1RQWUFfZWVHVExLTGpPd2ZJRXc4ektrYjVfN0p3LXc2bEdqTUhfcWY3TkhWSmZ2SDVPQVFZRU1SY1FxODFIMk5hOXhKNFZiLW9IUGsxRTN4aWNiR2N0SldWLVROcGlONHU3dUZ1R250dHpGOGdpbjN4a2JtZDNXNlpJZjgwNmN5Y0ZoS29ZRlM1U2xjVEx4QlpQcHZGcFVWNzhrYUsxQTJCZW1LbHljaWc1TURlbFo4RFoxdWdFLVc2bkh0UzBPd0NDR2Z1bkJKVVNEc1NneUVZdjNwell5VXUwYlI1VE9CYWkzVnpnODZfbGpNRXB0Vg?oc=5",
      "description": "<a href=\"https://news.google.com/rss/articles/CBMihAJBVV95cUxQNllldmI5Zzc4SEdKc1RQWUFfZWVHVExLTGpPd2ZJRXc4ektrYjVfN0p3LXc2bEdqTUhfcWY3TkhWSmZ2SDVPQVFZRU1SY1FxODFIMk5hOXhKNFZiLW9IUGsxRTN4aWNiR2N0SldWLVROcGlONHU3dUZ1R250dHpGOGdpbjN4a2JtZDNXNlpJZjgwNmN5Y0ZoS29ZRlM1U2xjVEx4QlpQcHZGcFVWNzhrYUsxQTJCZW1LbH",
      "publishedAt": "2026-07-02T03:26:27.000Z",
      "source": {
        "name": "Google News"
      },
      "urlToImage": null
    },
    {
      "title": "England captain Ben Stokes announces shock retirement from international cricket - AOL.com",
      "url": "https://news.google.com/rss/articles/CBMihwFBVV95cUxPSTQ3VDFhbmRtaEVFMS0ydnpnYTBGMVhldjlCTndBMXZDMFp0djROUXRKdFZMVXBnMDZDak5LOG9zTnQ0NWtNWGF4UGdiaUt2dUtCNVFmSTBWRGhNdDd6ZldRRVBma2FqVGxDZ0Y0ZUY2VVVSUHRXenN1REJ0VEY5Q1JBcUFRSTg?oc=5",
      "description": "<a href=\"https://news.google.com/rss/articles/CBMihwFBVV95cUxPSTQ3VDFhbmRtaEVFMS0ydnpnYTBGMVhldjlCTndBMXZDMFp0djROUXRKdFZMVXBnMDZDak5LOG9zTnQ0NWtNWGF4UGdiaUt2dUtCNVFmSTBWRGhNdDd6ZldRRVBma2FqVGxDZ0Y0ZUY2VVVSUHRXenN1REJ0VEY5Q1JBcUFRSTg?oc=5\" target=\"_blank\">England captain Ben Stokes announces shock r",
      "publishedAt": "2026-06-28T14:26:39.000Z",
      "source": {
        "name": "Google News"
      },
      "urlToImage": null
    },
    {
      "title": "Ben Stokes announces retirement from international cricket - MSN",
      "url": "https://news.google.com/rss/articles/CBMi8gFBVV95cUxNaVlCVTdMaHlzc0U0dWJwdUg5bkxKLThubXlMZGJPYnV0bEJ4VTBoSDZuOVRfdFozeTNvVElxS2hvZEtHc05iVE01elN0N3hobGx0eG9EOUliRllTTUhxNWE1WG1TTlR0RjJ3VUF4U0hZMFRsbVY3UjhoYV9VU3FkekhrX3J1TXVoVWRhN0IxZk9DREFuU2w3UTdKVTNubVpzWFZoclJQS1NQNkx3QVZreG5YQXk4dlhRVlpnVVhrUm1kbEdwa19BVHJxUUhLTlBSS2ZXVktXaEZTSHZMM29ab2RFWC0tU1h6VUhYRWdNUWM1dw?oc=5",
      "description": "<a href=\"https://news.google.com/rss/articles/CBMi8gFBVV95cUxNaVlCVTdMaHlzc0U0dWJwdUg5bkxKLThubXlMZGJPYnV0bEJ4VTBoSDZuOVRfdFozeTNvVElxS2hvZEtHc05iVE01elN0N3hobGx0eG9EOUliRllTTUhxNWE1WG1TTlR0RjJ3VUF4U0hZMFRsbVY3UjhoYV9VU3FkekhrX3J1TXVoVWRhN0IxZk9DREFuU2w3UTdKVTNubVpzWFZoclJQS1NQNkx3QVZreG5YQXk4dlhRVl",
      "publishedAt": "2026-06-29T14:18:05.000Z",
      "source": {
        "name": "Google News"
      },
      "urlToImage": null
    },
    {
      "title": "Sam Curran ready to fill all-rounder role as England seek Ben Stokes replacement - The Independent",
      "url": "https://news.google.com/rss/articles/CBMipwFBVV95cUxQbGpPVHNtVk5hSDlPck8yY1hoNFdBdzJKZlFCRVlqd0g1eGxUS3BwTGhCY1NLRF9BVmNXNTJyZ21GY3BtcEJKNUN2Z0lvWWxLZ2pPdllXUDItX2ZiaDAzX1VzR01fUlc5RFAzUzRpbFQ5ZktVeDF0amVhbFJ5UU1hNVZkazgzdm5iWmpJTHZqdnJDMzZ0cWFlSXFPejZnX0ZZdnVSS1J4RQ?oc=5",
      "description": "<a href=\"https://news.google.com/rss/articles/CBMipwFBVV95cUxQbGpPVHNtVk5hSDlPck8yY1hoNFdBdzJKZlFCRVlqd0g1eGxUS3BwTGhCY1NLRF9BVmNXNTJyZ21GY3BtcEJKNUN2Z0lvWWxLZ2pPdllXUDItX2ZiaDAzX1VzR01fUlc5RFAzUzRpbFQ5ZktVeDF0amVhbFJ5UU1hNVZkazgzdm5iWmpJTHZqdnJDMzZ0cWFlSXFPejZnX0ZZdnVSS1J4RQ?oc=5\" target=\"_blank\">S",
      "publishedAt": "2026-07-03T13:02:00.000Z",
      "source": {
        "name": "Google News"
      },
      "urlToImage": null
    },
    {
      "title": "Ben Stokes sends final farewell message to England fans after shock international retirement - Yahoo Sports UK",
      "url": "https://news.google.com/rss/articles/CBMihgFBVV95cUxNSzVDNXF3ZjQwdngtZFFiWTg2aXh1akw5Q2JXUW04MDZPS2phVmRPWFJEQUplVzV2RkJLSEZZMWk4Sl9MbURVLTd4OVJnRWVDZWw0dUlyYnNhdERBbkIwUDgwWndja1RmM2lpcmxndUxaZUlRRkV2V2Mzb2RkeGxMOUw5RjUxQQ?oc=5",
      "description": "<a href=\"https://news.google.com/rss/articles/CBMihgFBVV95cUxNSzVDNXF3ZjQwdngtZFFiWTg2aXh1akw5Q2JXUW04MDZPS2phVmRPWFJEQUplVzV2RkJLSEZZMWk4Sl9MbURVLTd4OVJnRWVDZWw0dUlyYnNhdERBbkIwUDgwWndja1RmM2lpcmxndUxaZUlRRkV2V2Mzb2RkeGxMOUw5RjUxQQ?oc=5\" target=\"_blank\">Ben Stokes sends final farewell message to En",
      "publishedAt": "2026-07-03T13:56:43.000Z",
      "source": {
        "name": "Google News"
      },
      "urlToImage": null
    }
  ],
  "culture": [
    {
      "title": "Greece - Cuisine, Culture, Traditions - Encyclopedia Britannica",
      "url": "https://news.google.com/rss/articles/CBMieEFVX3lxTFAzQjRQQy1DNXk5ejhKbUU3UkIzN1dqT2pwdWF3akZtWjNOZC1hdWd5aDhTVWFwUmt6YzhZMWJhUnpMTFJwNFZxa0k5ck5qQ1FpOG9SUldFNGItVG8ydkpSVHVxUDN3M1A1UG1jNEcwaGM3cVMycmItMQ?oc=5",
      "description": "<a href=\"https://news.google.com/rss/articles/CBMieEFVX3lxTFAzQjRQQy1DNXk5ejhKbUU3UkIzN1dqT2pwdWF3akZtWjNOZC1hdWd5aDhTVWFwUmt6YzhZMWJhUnpMTFJwNFZxa0k5ck5qQ1FpOG9SUldFNGItVG8ydkpSVHVxUDN3M1A1UG1jNEcwaGM3cVMycmItMQ?oc=5\" target=\"_blank\">Greece - Cuisine, Culture, Traditions</a>&nbsp;&nbsp;<font color=",
      "publishedAt": "2026-07-01T05:00:00.000Z",
      "source": {
        "name": "Google News"
      },
      "urlToImage": null
    },
    {
      "title": "Sri Lanka - Culture, Religion, Cuisine - Encyclopedia Britannica",
      "url": "https://news.google.com/rss/articles/CBMiZ0FVX3lxTE01bFpQQVBTdFZoUFg1UWg4TWVVRTRtTDRLQUk4T0FtcFRaTmJkTFVsd3ZKbnFHSUlZTE5LcnZrYml5dHV5SmN1MElrQ2dWb0xWcExQRlZHZU41eXRhaGE3MHBSQVZEUzA?oc=5",
      "description": "<a href=\"https://news.google.com/rss/articles/CBMiZ0FVX3lxTE01bFpQQVBTdFZoUFg1UWg4TWVVRTRtTDRLQUk4T0FtcFRaTmJkTFVsd3ZKbnFHSUlZTE5LcnZrYml5dHV5SmN1MElrQ2dWb0xWcExQRlZHZU41eXRhaGE3MHBSQVZEUzA?oc=5\" target=\"_blank\">Sri Lanka - Culture, Religion, Cuisine</a>&nbsp;&nbsp;<font color=\"#6f6f6f\">Encyclopedia",
      "publishedAt": "2026-07-01T05:00:00.000Z",
      "source": {
        "name": "Google News"
      },
      "urlToImage": null
    },
    {
      "title": "New South Wales - Culture, Diversity, Aborigines - Encyclopedia Britannica",
      "url": "https://news.google.com/rss/articles/CBMib0FVX3lxTFBQOXAzZUNkMWN6b05nZ1g4ajB0M2VUMzR5dUIxYjB0bnVBd2ROYW5ZcGJyVGZ2YjRmZGxONXd2UUVPZ0t2dmVZX2Z0alRxZ2hiTUNWcl9Jd1FkS05pQ1p3X2pzczM4amlkLTN6dXZnZw?oc=5",
      "description": "<a href=\"https://news.google.com/rss/articles/CBMib0FVX3lxTFBQOXAzZUNkMWN6b05nZ1g4ajB0M2VUMzR5dUIxYjB0bnVBd2ROYW5ZcGJyVGZ2YjRmZGxONXd2UUVPZ0t2dmVZX2Z0alRxZ2hiTUNWcl9Jd1FkS05pQ1p3X2pzczM4amlkLTN6dXZnZw?oc=5\" target=\"_blank\">New South Wales - Culture, Diversity, Aborigines</a>&nbsp;&nbsp;<font color=\"",
      "publishedAt": "2026-07-01T05:00:00.000Z",
      "source": {
        "name": "Google News"
      },
      "urlToImage": null
    },
    {
      "title": "Mysore Palace: Why this royal landmark remains one of India's most visited attractions - Firstpost",
      "url": "https://news.google.com/rss/articles/CBMivgFBVV95cUxNRjV0a3BDMFRGdG42eHBDTlZpWVgxaHFNQU83ZGhsaWNfUjVmLUQ2a2FyczB0MFQzeEFZeGtYTXBmMDJXaWFlaUlHbmw2am9ZT3ZmcjB5TzRISmpJV2FEMGk1RWhvNHlnb2hlaXhXQUZxMHZzS0c1ZlhEMFgxbGZ3bk9ELXRIMmh6a2ZXYTMtZHh5QlZsek15TUViTUR5M2dwbllfbWU0bWowdC16N0NYREhBMU1nTUViaXRxeFFB0gHDAUFVX3lxTFA1WG1RMkMyNjFWcmo1azBSeUJRajc5U1JMZFZwdEh5U3Qwald4TVg3M3JJVEEtd2ZfalM5N3BDd2wyOFBsSGVvZWRYbHU5MDF2Q0VZNWhLU241M3dtUWEzakRuZXpic1NkVHBvTlAzNWNWQUQ2SmVxR0hwcTFjTk1kVHRkTWlkRXpnWllfeVBpdVJUbGNqc1N2TFRST0sxQTd0N011SVRpeXEtVXhRcDVJdXBMOVR6YmJkVGhSdUlYOFpobw?oc=5",
      "description": "<a href=\"https://news.google.com/rss/articles/CBMivgFBVV95cUxNRjV0a3BDMFRGdG42eHBDTlZpWVgxaHFNQU83ZGhsaWNfUjVmLUQ2a2FyczB0MFQzeEFZeGtYTXBmMDJXaWFlaUlHbmw2am9ZT3ZmcjB5TzRISmpJV2FEMGk1RWhvNHlnb2hlaXhXQUZxMHZzS0c1ZlhEMFgxbGZ3bk9ELXRIMmh6a2ZXYTMtZHh5QlZsek15TUViTUR5M2dwbllfbWU0bWowdC16N0NYREhBMU1nTUViaX",
      "publishedAt": "2026-06-16T14:16:23.000Z",
      "source": {
        "name": "Google News"
      },
      "urlToImage": null
    },
    {
      "title": "Cricket thrives in South Florida as Caribbean families pass the game to a new generation - NBC 6 South Florida",
      "url": "https://news.google.com/rss/articles/CBMi1gFBVV95cUxNSjdaSGo5MGVfbG1vbk9GWnRXbHRvNGhMc0h2ZkZITk5JYUIzWWQ3R2o1enYwZVExQnprTUVmendrc09TSjBKUTBaaXMwNTlhakZuYzFjenI4LTRHd0ppcm5mR1d5N3I3MkwwYi1MaXFVS285eXlqbU50OWpxYnl5TTQwS3ZVZzZCc2RKcGZ2MTk2TU5qUEd3b05uLU9sR0dMZ0VTWEhQdGZjaWJWd1lrbFlsVDZGUFpHWlYwUDFDRkhpX2MxejV5bEx5ZnVPdEE5aFhuc0J30gHWAUFVX3lxTE1KN1pIajkwZV9sbW9uT0ZadFdsdG80aExzSHZmRkhOTklhQjNZZDdHajV6djBlUTFCemtNRWZ6d2tzT1NKMEpRMFppczA1OWFqRm5jMWN6cjgtNEd3SmlybmZHV3k3cjcyTDBiLUxpcVVLbzl5eWptTnQ5anFieXlNNDBLdlVnNkJzZEpwZnYxOTZNTmpQR3dvTm4tT2xHR0xnRVNYSFB0ZmNpYlZ3WWtsWWxUNkZQWkdaVjBQMUNGSGlfYzF6NXlsTHlmdU90QTloWG5zQnc?oc=5",
      "description": "<a href=\"https://news.google.com/rss/articles/CBMi1gFBVV95cUxNSjdaSGo5MGVfbG1vbk9GWnRXbHRvNGhMc0h2ZkZITk5JYUIzWWQ3R2o1enYwZVExQnprTUVmendrc09TSjBKUTBaaXMwNTlhakZuYzFjenI4LTRHd0ppcm5mR1d5N3I3MkwwYi1MaXFVS285eXlqbU50OWpxYnl5TTQwS3ZVZzZCc2RKcGZ2MTk2TU5qUEd3b05uLU9sR0dMZ0VTWEhQdGZjaWJWd1lrbFlsVDZGUFpHWl",
      "publishedAt": "2026-07-01T14:46:45.000Z",
      "source": {
        "name": "Google News"
      },
      "urlToImage": null
    },
    {
      "title": "Legacy Of Masked Dances - The Rising Nepal",
      "url": "https://news.google.com/rss/articles/CBMiUEFVX3lxTFBKVHdfNE0zLWZ3SThjd3MxZENBTGxHWlE2S1VFNW5rSG1ZZm83QlI0ekVITExhZm50OWowVnhfNm5rUjlLdnVLQnpGVVdzN0kz?oc=5",
      "description": "<a href=\"https://news.google.com/rss/articles/CBMiUEFVX3lxTFBKVHdfNE0zLWZ3SThjd3MxZENBTGxHWlE2S1VFNW5rSG1ZZm83QlI0ekVITExhZm50OWowVnhfNm5rUjlLdnVLQnpGVVdzN0kz?oc=5\" target=\"_blank\">Legacy Of Masked Dances</a>&nbsp;&nbsp;<font color=\"#6f6f6f\">The Rising Nepal</font>",
      "publishedAt": "2026-06-19T02:50:59.000Z",
      "source": {
        "name": "Google News"
      },
      "urlToImage": null
    },
    {
      "title": "Traffic cones on statues and a sea of orange: The traditions taking over the World Cup - ABC News & Headlines – Australian Broadcasting Corporation",
      "url": "https://news.google.com/rss/articles/CBMiqgFBVV95cUxQbFpiUHNZMHJMVHkyYTdwZ1dOdmZUZHk5TUt0YVBjMWdIZVNXV1RDaEg2cVVxNlh1b3JiamM5OTQxcUxMOXljOENfcW0xa1RRdVl5YWZBSTdvMGd6cFNaZzFCQ1VZT0VCVm5DR2tVaUczTWl4dUg5TjVFTE5vSXhjZDBYX05TMW05enJqV19OeXc0QWV1YTFpWXNQUkJaSmRxZ0dySFV1REFsUQ?oc=5",
      "description": "<a href=\"https://news.google.com/rss/articles/CBMiqgFBVV95cUxQbFpiUHNZMHJMVHkyYTdwZ1dOdmZUZHk5TUt0YVBjMWdIZVNXV1RDaEg2cVVxNlh1b3JiamM5OTQxcUxMOXljOENfcW0xa1RRdVl5YWZBSTdvMGd6cFNaZzFCQ1VZT0VCVm5DR2tVaUczTWl4dUg5TjVFTE5vSXhjZDBYX05TMW05enJqV19OeXc0QWV1YTFpWXNQUkJaSmRxZ0dySFV1REFsUQ?oc=5\" target=\"_blan",
      "publishedAt": "2026-06-24T07:00:00.000Z",
      "source": {
        "name": "Google News"
      },
      "urlToImage": null
    },
    {
      "title": "Indian Army hosts lecture on Tripura’s cultural heritage at Agartala Military Station - India Today NE",
      "url": "https://news.google.com/rss/articles/CBMi3gFBVV95cUxPTVc1MmZXOTNQay1PVGZyeVFjTlBzRkpjYlEwTXUyNnN4Ry1lN0xoVkFZY3lnZ3RIaTdiRzU1bVpvQXdwc1o0LS1XZFlieXdCZzJoMURTUEpWeDM0bEM2dzNqV3NGQmttbkpLOUtIYXNVTUhFNld6alFXX1ZMcTQ1b0x5V29yNjE3RUZKdmdyWG1XeEtSLUtKdzJSUUZxcERNenNIRzZZbDhOaVZuckVFUDNTc05fLVJobzNwMVRRamFIZE9LbWpyX0VsdFg3Zm5HZEFzc2UzZjhVNVR0d2fSAeMBQVVfeXFMT05yNHpibHBfRVNTbEgtUW5ZTHVHVFBiR1F3blRpV3AwSUFMWEF4QjNFbWJYSmRTNTVzZzF4UDN1X3ViRV9IelRud3FhSGhNUkhNNE5DbmgwLVUyWWV5b01yWEx4NzdENHhxNkFFZVNZam1HemdlekRXaTBSenpuTmt3b2ZfYXAxcUd2MWZsY1NRc2pIQ18tcjhkVmpJT1hKN2lDYlNUbjlIRkZSSHZwUDdtSDJfVXFGOXZYRThsczdNMkExR3g2YVFZbjZsRm81OV9pQW13WEZwOThUc2VGLTFhX1E?oc=5",
      "description": "<a href=\"https://news.google.com/rss/articles/CBMi3gFBVV95cUxPTVc1MmZXOTNQay1PVGZyeVFjTlBzRkpjYlEwTXUyNnN4Ry1lN0xoVkFZY3lnZ3RIaTdiRzU1bVpvQXdwc1o0LS1XZFlieXdCZzJoMURTUEpWeDM0bEM2dzNqV3NGQmttbkpLOUtIYXNVTUhFNld6alFXX1ZMcTQ1b0x5V29yNjE3RUZKdmdyWG1XeEtSLUtKdzJSUUZxcERNenNIRzZZbDhOaVZuckVFUDNTc05fLVJobz",
      "publishedAt": "2026-06-16T07:00:00.000Z",
      "source": {
        "name": "Google News"
      },
      "urlToImage": null
    },
    {
      "title": "Red Shield Division hosts lecture on Tripura's rich cultural heritage - Asianet Newsable",
      "url": "https://news.google.com/rss/articles/CBMixgFBVV95cUxNTzVaUi1qYjEySlVyTmVSME1LaHhZZG11WG0tb203UjI4NkYxRFVvWmQtTDlFRTdoc3A3MzBqQnlkbjE3TWw1M0pTNXp2Smh5cVM4V05senJSMmxRWVZZU2dWTW1VN1lhQmdmcExhQ1otVlJVaElnQTNnUmd5Mmc0dVJDcXJRV3FwWVM0dU9NNVBlclpmNnVqejBHRldHVkNIQmo4ZXlNclF2bEQ1eHdGU3pDdW5uRE54LWRlcFh2ZnJnWkhYTXfSAcsBQVVfeXFMT29CUURmSXRpQ2x4aEI0ei04ZnoxNHdUSG1qR0hFNmhReFhoUzZNWUdoVzVIMkl3RlRPUG9KUk93LTVuY2VqNkFFbVNzenFwa3hzUGVmb25uYjhXMFg5MkVqa0VwVkQ5LTdTQTBBQV9saHFKNjFsM2hzOHdBMkh0NS1ZY0NvSGpQOW9mamd2QXcxeDF3dy1vMFViVVBYVDA5MzFlaWhsc2FRRmExRFhZaGpMT2dpRi0zV0I4dkxLLUFPSjhHS3U2UFNNUGc?oc=5",
      "description": "<a href=\"https://news.google.com/rss/articles/CBMixgFBVV95cUxNTzVaUi1qYjEySlVyTmVSME1LaHhZZG11WG0tb203UjI4NkYxRFVvWmQtTDlFRTdoc3A3MzBqQnlkbjE3TWw1M0pTNXp2Smh5cVM4V05senJSMmxRWVZZU2dWTW1VN1lhQmdmcExhQ1otVlJVaElnQTNnUmd5Mmc0dVJDcXJRV3FwWVM0dU9NNVBlclpmNnVqejBHRldHVkNIQmo4ZXlNclF2bEQ1eHdGU3pDdW5uRE54LW",
      "publishedAt": "2026-06-17T02:00:18.000Z",
      "source": {
        "name": "Google News"
      },
      "urlToImage": null
    },
    {
      "title": "Twenty20 cricket | Rules, History, World Cup, 2026, Scores, Matches, Highlights, Rankings, Schedule, & Facts - Encyclopedia Britannica",
      "url": "https://news.google.com/rss/articles/CBMiX0FVX3lxTE5Odk91S3pNRGZOaml6OS16elJSRHhxMkxaZ09ERmFveVNnU2FuNmRaSGk4OVZvSGdFb1hveG1DRGZWZi1XQzVxNUdlV08tLXRDS2Q5U1docjJKWHY4b0c4?oc=5",
      "description": "<a href=\"https://news.google.com/rss/articles/CBMiX0FVX3lxTE5Odk91S3pNRGZOaml6OS16elJSRHhxMkxaZ09ERmFveVNnU2FuNmRaSGk4OVZvSGdFb1hveG1DRGZWZi1XQzVxNUdlV08tLXRDS2Q5U1docjJKWHY4b0c4?oc=5\" target=\"_blank\">Twenty20 cricket | Rules, History, World Cup, 2026, Scores, Matches, Highlights, Rankings, Schedule",
      "publishedAt": "2026-06-25T07:00:00.000Z",
      "source": {
        "name": "Google News"
      },
      "urlToImage": null
    },
    {
      "title": "Cricket’s Canadian surge: the top 5 rules every beginner should know - Cricket World",
      "url": "https://news.google.com/rss/articles/CBMiqwFBVV95cUxNS1g0Qkt3MThTSmpreHJ4VHk2aEFQeEZ3UmhvOHFGWkt0NzV6YmxVWjdIb3NaeW1mZEFSdzY2M2VvTVU3am91OHk2R21UVUo5VGZKNnJ1RmhJNXZfUk1xbDRXM3JkaHZZdk1LNW1md1NSSGJiblY1Y0paWmJMekw5T0lVUmF5V2pQcWppYWhHaXRRNXh0VVN4ZUItb0tqdTNxTGxxaGRfdGxtYVE?oc=5",
      "description": "<a href=\"https://news.google.com/rss/articles/CBMiqwFBVV95cUxNS1g0Qkt3MThTSmpreHJ4VHk2aEFQeEZ3UmhvOHFGWkt0NzV6YmxVWjdIb3NaeW1mZEFSdzY2M2VvTVU3am91OHk2R21UVUo5VGZKNnJ1RmhJNXZfUk1xbDRXM3JkaHZZdk1LNW1md1NSSGJiblY1Y0paWmJMekw5T0lVUmF5V2pQcWppYWhHaXRRNXh0VVN4ZUItb0tqdTNxTGxxaGRfdGxtYVE?oc=5\" target=\"_bla",
      "publishedAt": "2026-06-04T07:00:00.000Z",
      "source": {
        "name": "Google News"
      },
      "urlToImage": null
    },
    {
      "title": "Cricket World Test Championship Explained: Format, Points and Final Qualification - World In Sport",
      "url": "https://news.google.com/rss/articles/CBMidkFVX3lxTE9sNnRwN3FNVXZXNUk0a3FUNDJoTTU2b0ZHa3pSQmtDaWZReUsxZEl2MUMwTl9XNC11UmFLSVpWWjkyMURPOFhsWUdDc2F2SXVOUGM0M3M4M3VqTFZEeDJmTS1pOHRwYjJrZTNkS3ZZOGd1WkFxS0E?oc=5",
      "description": "<a href=\"https://news.google.com/rss/articles/CBMidkFVX3lxTE9sNnRwN3FNVXZXNUk0a3FUNDJoTTU2b0ZHa3pSQmtDaWZReUsxZEl2MUMwTl9XNC11UmFLSVpWWjkyMURPOFhsWUdDc2F2SXVOUGM0M3M4M3VqTFZEeDJmTS1pOHRwYjJrZTNkS3ZZOGd1WkFxS0E?oc=5\" target=\"_blank\">Cricket World Test Championship Explained: Format, Points and Final ",
      "publishedAt": "2026-06-12T07:00:00.000Z",
      "source": {
        "name": "Google News"
      },
      "urlToImage": null
    },
    {
      "title": "Major records that may be broken at Women’s T20 World Cup - ICC",
      "url": "https://news.google.com/rss/articles/CBMivAFBVV95cUxQQ0s3RjVMVElTQVRodmdQZWdlOElrSkxoN1ctcHZpTUpwUF9QRHo2QTZkdFZUaDBXS3J3NEZsMHdEeG1tTTRCM3piRDl3LUN6Y2doTkhPekVMTWtyMmVaRGxteWVwenZmLXlETTZmeEJsVkxJZGljMUxJQmFXQWhNYkNHelNuOFNockpPclBhRlBQWUd5NGs2NG1LZWlvS29GREZ4Mnh0TkR2b1BmajBxQUVqUThYSEZNNHdpTQ?oc=5",
      "description": "<a href=\"https://news.google.com/rss/articles/CBMivAFBVV95cUxQQ0s3RjVMVElTQVRodmdQZWdlOElrSkxoN1ctcHZpTUpwUF9QRHo2QTZkdFZUaDBXS3J3NEZsMHdEeG1tTTRCM3piRDl3LUN6Y2doTkhPekVMTWtyMmVaRGxteWVwenZmLXlETTZmeEJsVkxJZGljMUxJQmFXQWhNYkNHelNuOFNockpPclBhRlBQWUd5NGs2NG1LZWlvS29GREZ4Mnh0TkR2b1BmajBxQUVqUThYSEZNNH",
      "publishedAt": "2026-06-04T07:00:00.000Z",
      "source": {
        "name": "Google News"
      },
      "urlToImage": null
    },
    {
      "title": "The ‘game-changing’ Women’s T20 World Cup: Record ticket sales, a Lionesses moment and West End witches - The New York Times",
      "url": "https://news.google.com/rss/articles/CBMinwFBVV95cUxOck5OMVk4cTh4Tk9ndFJ4X2dWQm5VZUtUckw1dThCd0VlLTNaeGlha3ZTb0F1eUduRWFiRDFMck83cHItVnI2Ym1HLUw3cDRVaWNnX3JBQVpHbGRWYlZCR1lWUTlTZGNVd1ExNlYyZGd1d3dZSjZmMFpNUFRxc1hkdHVmWlZiWUpwdmtpSGNxekVNcmh6QU8zbmV0NXRaVmM?oc=5",
      "description": "<a href=\"https://news.google.com/rss/articles/CBMinwFBVV95cUxOck5OMVk4cTh4Tk9ndFJ4X2dWQm5VZUtUckw1dThCd0VlLTNaeGlha3ZTb0F1eUduRWFiRDFMck83cHItVnI2Ym1HLUw3cDRVaWNnX3JBQVpHbGRWYlZCR1lWUTlTZGNVd1ExNlYyZGd1d3dZSjZmMFpNUFRxc1hkdHVmWlZiWUpwdmtpSGNxekVNcmh6QU8zbmV0NXRaVmM?oc=5\" target=\"_blank\">The ‘game-ch",
      "publishedAt": "2026-06-13T07:00:00.000Z",
      "source": {
        "name": "Google News"
      },
      "urlToImage": null
    },
    {
      "title": "'Ek Bihari, sab pe bhari': After a record-breaking IPL season, Vaibhav Sooryavanshi gets his India moment - The Times of India",
      "url": "https://news.google.com/rss/articles/CBMijwJBVV95cUxNeFNxdkVaV3hqcUZtajU4ZHB3U2o1X09taE9wLVRWcUJNcWYtcEp6UENhR0JBeDZDOU16MEFrbDdhTVN2UWJ0MFZzTFV2QnFnb1E3VHc2eS1DYXA4bFJlZW56N1FrUkFJY0o0dnlpMmJmblo0OXVFM2NVYXRma1lYQTVMNUZvUFg2aXNlVHRudW5rQ21XN24xU1ZqYTVuSGJ3clZkNnBsSmpZOHBfa1FHdnpCeV9MR2Z4TjlvOTAySmVsTTdXajctUzhFUWhnUGdnY3VwQV94NXFwSEkyWjNUT2MyNzh2TzVhdnd2TVdscndwSV94UkpucUxIaUs4Q0ZkVU9DNktZSDNUUTVzem5Z?oc=5",
      "description": "<a href=\"https://news.google.com/rss/articles/CBMijwJBVV95cUxNeFNxdkVaV3hqcUZtajU4ZHB3U2o1X09taE9wLVRWcUJNcWYtcEp6UENhR0JBeDZDOU16MEFrbDdhTVN2UWJ0MFZzTFV2QnFnb1E3VHc2eS1DYXA4bFJlZW56N1FrUkFJY0o0dnlpMmJmblo0OXVFM2NVYXRma1lYQTVMNUZvUFg2aXNlVHRudW5rQ21XN24xU1ZqYTVuSGJ3clZkNnBsSmpZOHBfa1FHdnpCeV9MR2Z4Tj",
      "publishedAt": "2026-06-06T07:00:00.000Z",
      "source": {
        "name": "Google News"
      },
      "urlToImage": null
    },
    {
      "title": "How Many Times Have Ireland Beaten BIG Teams in T20I Cricket? - Sportsdunia",
      "url": "https://news.google.com/rss/articles/CBMimAFBVV95cUxQUzBzd0NQSDVUNXpqNW5kUk9sakNReWRVZXh0a2pWVThRbkJGaDBnZHRnVEh1eEUtWHROR1U5cVowNGN5V1AyXzNHd3R5dlBVSXZzVHNRXzVKQjdVeGRwRWl5YXMwTmpxMWszeE5lQ0NsVlpESVptX05iLVZZUWlTcTJfa3lFM3FyV3JRcU84S0hvSzROam44TA?oc=5",
      "description": "<a href=\"https://news.google.com/rss/articles/CBMimAFBVV95cUxQUzBzd0NQSDVUNXpqNW5kUk9sakNReWRVZXh0a2pWVThRbkJGaDBnZHRnVEh1eEUtWHROR1U5cVowNGN5V1AyXzNHd3R5dlBVSXZzVHNRXzVKQjdVeGRwRWl5YXMwTmpxMWszeE5lQ0NsVlpESVptX05iLVZZUWlTcTJfa3lFM3FyV3JRcU84S0hvSzROam44TA?oc=5\" target=\"_blank\">How Many Times Have I",
      "publishedAt": "2026-06-28T18:17:28.000Z",
      "source": {
        "name": "Google News"
      },
      "urlToImage": null
    }
  ],
  "videos": []
}