{
  "lastUpdated": "2026-06-13T10:19:31.219Z",
  "articles": [
    {
      "title": "Ireland bowl against Scotland in their first World Cup meeting",
      "url": "https://www.espncricinfo.com/ci/content/story/1540965.html?ex_cid=OTC-RSS",
      "description": "Ireland and Scotland have never faced each other before in a women's World Cup, ODIs or T20Is",
      "publishedAt": "2026-06-13T09:51:33.000Z",
      "source": {
        "name": "ESPNcricinfo"
      },
      "urlToImage": null
    },
    {
      "title": "Nayeem Hasan allegedly assaulted by policemen in Chattogram",
      "url": "https://www.espncricinfo.com/ci/content/story/1540830.html?ex_cid=OTC-RSS",
      "description": "The auto-rickshaw Nayeem Hasan was returning home from the airport in was stopped by law-enforcement officials, who proceeded to physically assault the cricketer",
      "publishedAt": "2026-06-13T07:25:20.000Z",
      "source": {
        "name": "ESPNcricinfo"
      },
      "urlToImage": null
    },
    {
      "title": "D-day looms for Australian cricket in BBL privatisation push",
      "url": "https://www.espncricinfo.com/ci/content/story/1540661.html?ex_cid=OTC-RSS",
      "description": "A key meeting of state chairs takes place in Melbourne on Monday in what has become a troubled process",
      "publishedAt": "2026-06-13T01:45:29.000Z",
      "source": {
        "name": "ESPNcricinfo"
      },
      "urlToImage": null
    },
    {
      "title": "India face test of depth in first-ever ODI series against Afghanistan",
      "url": "https://www.espncricinfo.com/ci/content/story/1540722.html?ex_cid=OTC-RSS",
      "description": "Afghanistan will lean on their ODI experience in India, who will not have Kohli, Hardik, Siraj and Bumrah",
      "publishedAt": "2026-06-13T09:17:55.000Z",
      "source": {
        "name": "ESPNcricinfo"
      },
      "urlToImage": null
    },
    {
      "title": "Saturday at T20 World Cup: Ismail's return, reruns of 2024 semis, and some rain",
      "url": "https://www.espncricinfo.com/ci/content/story/1540724.html?ex_cid=OTC-RSS",
      "description": "A look at the first triple-header of the Women's T20 World Cup",
      "publishedAt": "2026-06-13T08:12:06.000Z",
      "source": {
        "name": "ESPNcricinfo"
      },
      "urlToImage": null
    },
    {
      "title": "Kane Williamson retires from international cricket",
      "url": "https://www.espncricinfo.com/ci/content/story/1540723.html?ex_cid=OTC-RSS",
      "description": "New Zealand's record run-scorer opts out of completing ongoing Test series in England",
      "publishedAt": "2026-06-12T15:17:10.000Z",
      "source": {
        "name": "ESPNcricinfo"
      },
      "urlToImage": null
    },
    {
      "title": "Mehidy taken to hospital after being hit on the head by bouncer",
      "url": "https://www.espncricinfo.com/ci/content/story/1540534.html?ex_cid=OTC-RSS",
      "description": "Mehidy had a concussion, the team physio said, and will remain in hospital for 24 hours",
      "publishedAt": "2026-06-12T13:41:11.000Z",
      "source": {
        "name": "ESPNcricinfo"
      },
      "urlToImage": null
    },
    {
      "title": "Taskin, Mustafizur set up famous series win for Bangladesh",
      "url": "https://www.espncricinfo.com/ci/content/story/1540450.html?ex_cid=OTC-RSS",
      "description": "Australia crashed to 0 for 3 and despite a century stand from Labuschagne and Bartlett, the home side came out comfortable winners",
      "publishedAt": "2026-06-11T15:07:47.000Z",
      "source": {
        "name": "ESPNcricinfo"
      },
      "urlToImage": null
    },
    {
      "title": "Australia seek response as Bangladesh close in on landmark series win",
      "url": "https://www.espncricinfo.com/ci/content/story/1540359.html?ex_cid=OTC-RSS",
      "description": "Confident hosts will hope for another complete performance as they eye a maiden ODI series win against Australia",
      "publishedAt": "2026-06-10T05:43:55.000Z",
      "source": {
        "name": "ESPNcricinfo"
      },
      "urlToImage": null
    },
    {
      "title": "Rana and Mosaddek star as Bangladesh end 21-year wait with crushing win",
      "url": "https://www.espncricinfo.com/ci/content/story/1540267.html?ex_cid=OTC-RSS",
      "description": "Australia dropped four catches then lost early wickets in the chase before Nahid Rana's pace did the damage",
      "publishedAt": "2026-06-09T14:26:41.000Z",
      "source": {
        "name": "ESPNcricinfo"
      },
      "urlToImage": null
    },
    {
      "title": "The Hundred Men's 2026: Zak Crawley confirmed as Sunrisers Leeds captain ahead of Harry Brook",
      "url": "https://www.crictracker.com/cricket-news/the-hundred-mens-2026-zak-crawley-confirmed-as-sunrisers-leeds-captain-ahead-of-harry-brook/",
      "description": "Crawley was signed by the Headingley-based franchise for GBP 180,000, making him their fifth-most expensive signing in the auction.",
      "publishedAt": "2026-06-13T09:43:18.000Z",
      "source": {
        "name": "CricTracker"
      },
      "urlToImage": null
    },
    {
      "title": "‘You inspired countless girls’ - Alia Bhatt hails Jemimah Rodrigues’ heroics against Australia in Women’s World Cup 2025",
      "url": "https://www.crictracker.com/cricket-news/you-inspired-countless-girls-alia-bhatt-hails-jemimah-rodrigues-heroics-against-australia-in-womens-world-cup-2025-1825/",
      "description": "“Jemimah, the world knows about your innings against Australia. That knock was too spectacular, beyond words. I am sure that day, you inspired countless young girls,\" said Alia.",
      "publishedAt": "2026-06-13T09:39:59.000Z",
      "source": {
        "name": "CricTracker"
      },
      "urlToImage": null
    },
    {
      "title": "Australian Cricket's privatisation push nears key vote as Todd Greenberg reaffirms long-term vision",
      "url": "https://www.crictracker.com/cricket-news/australian-crickets-privatisation-push-nears-key-vote-as-todd-greenberg-reaffirms-long-term-vision/",
      "description": "\"We have an eye on the long-term future. And one thing is absolutely clear - to maintain Australia's position at the top and keep growing the game's popularity,\" said Greenberg.",
      "publishedAt": "2026-06-13T06:59:59.000Z",
      "source": {
        "name": "CricTracker"
      },
      "urlToImage": null
    },
    {
      "title": "‘For the family’ - Danni Wyatt-Hodge dedicates stunning World Cup century to daughter Daisy",
      "url": "https://www.crictracker.com/cricket-news/for-the-family-danni-wyatt-hodge-dedicates-stunning-world-cup-century-to-daughter-daisy-5170/",
      "description": "The experienced right-hander played a match-winning knock of 105* to help England begin their home World Cup campaign in dominant fashion.",
      "publishedAt": "2026-06-13T06:16:28.000Z",
      "source": {
        "name": "CricTracker"
      },
      "urlToImage": null
    },
    {
      "title": "English cricket has quickly found itself in another mess. Ben Stokes is in the middle of it - New Haven Register",
      "url": "https://news.google.com/rss/articles/CBMinwFBVV95cUxOM19kWXJISHhaR1ViRC1KTmFOaWJGakx2QXBuN0xfeHZHMGJ2TVRGd1g2T1RHZTZoVk1ROUlrYXk1U2VPOHNiUnFVaFd5d3BBMTdUc3I3bUxFU1ZZYXEya1lFSndKb2Q5dVVVeGlzVWM3TGZQZjN6eVRpYjNFLVZYd1JFWG0zdkpQazZLWGZDanJPN0FRMm85ZkpXQ2JmWmM?oc=5",
      "description": "<a href=\"https://news.google.com/rss/articles/CBMinwFBVV95cUxOM19kWXJISHhaR1ViRC1KTmFOaWJGakx2QXBuN0xfeHZHMGJ2TVRGd1g2T1RHZTZoVk1ROUlrYXk1U2VPOHNiUnFVaFd5d3BBMTdUc3I3bUxFU1ZZYXEya1lFSndKb2Q5dVVVeGlzVWM3TGZQZjN6eVRpYjNFLVZYd1JFWG0zdkpQazZLWGZDanJPN0FRMm85ZkpXQ2JmWmM?oc=5\" target=\"_blank\">English cric",
      "publishedAt": "2026-06-11T12:48:28.000Z",
      "source": {
        "name": "Google News"
      },
      "urlToImage": null
    },
    {
      "title": "England vs Sri Lanka Highlights, ICC Women's T20 World Cup 2026: Danni Wyatt-Hodge Slams Stunning 105, England Seal Huge Win - NDTV Sports",
      "url": "https://news.google.com/rss/articles/CBMijgJBVV95cUxNNU5fQVNIdTZfQkwxRWMwX3d1MUZvTjhCc0JBdEpIbjF6aTg4TE1PcGtMeTI4V1h2ZUVxZ3oteHJYcFUyLUFCRnJvbVFkNWQ4ajNzYmNWNHRJYWhPWlVxQ2E2S24xUW5PV1lJZUd5cGwyd0twcmo5SXU3UTBNYloyY2ZZd3VldjNQTmZyVk9qajQyekRONEFZbXc1WWVNandPdjFhM1BpV1NFei1IbG9RdVlSeVNrSHcwV0REVzdKSnQzWGN6NWFVam1lS3hSUmdJdktQSV9iVHF2TWtmYnFWZlpxWjNra0JjNHB0MExKYUs4U25LdzJtQVByZFQ3cHJBMnJTdXU0OUljaDV3LVE?oc=5",
      "description": "<a href=\"https://news.google.com/rss/articles/CBMijgJBVV95cUxNNU5fQVNIdTZfQkwxRWMwX3d1MUZvTjhCc0JBdEpIbjF6aTg4TE1PcGtMeTI4V1h2ZUVxZ3oteHJYcFUyLUFCRnJvbVFkNWQ4ajNzYmNWNHRJYWhPWlVxQ2E2S24xUW5PV1lJZUd5cGwyd0twcmo5SXU3UTBNYloyY2ZZd3VldjNQTmZyVk9qajQyekRONEFZbXc1WWVNandPdjFhM1BpV1NFei1IbG9RdVlSeVNrSHcwV0",
      "publishedAt": "2026-06-12T21:43:00.000Z",
      "source": {
        "name": "Google News"
      },
      "urlToImage": null
    },
    {
      "title": "ICC Women's T20 World Cup 2026 FAQs: The complete guide to schedule, format, teams, venues and title contenders - Firstpost",
      "url": "https://news.google.com/rss/articles/CBMi5gFBVV95cUxQcGx3aDRLNnhaLURCeDdWR1ltSmlhNUxXeVNhdk5OOFBiNnpqZWFCZVNOaGtSZDYxVWp5T2QxeDBRXzA3QUJpX0pld090MnBXQ1ZqRUJWal9EOU4tUnZNUWRtSTVaYXh5SVBoYVFkUkxReThpTUlqZE1rR29VQzJ0Ml9Ib0g1ZlUzenZ4ZFhEQU90VFUwRDFIWGFYalN5VHQxeS1FWjBkLVBKYTQ5MFY2LUd6M2FnY1h1bzh2amNVMUZmeDFPNjJ5Y2EzYnlJVDBaSW8wZndkQUk5MFIxMmJrRGxob0ZFQdIB6wFBVV95cUxPd21aZG5sUHNXWld1U0c4emFiQzRfalJ5OGk0dENKTDJCMTR1d1lJdG9Hb2VwcGFaUnZFVk5EWlZLR1BYM0I4SlNacWllTy05dFJNdFpXQktmeUkxNm03bDVob0hDQWtkc0lNOG5XU0NOWElvS2p5Sm1LSUZHeEVIVWJjTEtFSl9jNDZwdGpJU0l5X1otQWlHdlNYQkYwbW43VWZzcUR1TGJ2ZUxOVkl6Z21TNTVVOVdtYkxyN01aNG9uTkRSbVpGX0oyYmdoLVNkQ0pDcWpKbUZVSnBWM3pPYjczb1RFMmJaTG9N?oc=5",
      "description": "<a href=\"https://news.google.com/rss/articles/CBMi5gFBVV95cUxQcGx3aDRLNnhaLURCeDdWR1ltSmlhNUxXeVNhdk5OOFBiNnpqZWFCZVNOaGtSZDYxVWp5T2QxeDBRXzA3QUJpX0pld090MnBXQ1ZqRUJWal9EOU4tUnZNUWRtSTVaYXh5SVBoYVFkUkxReThpTUlqZE1rR29VQzJ0Ml9Ib0g1ZlUzenZ4ZFhEQU90VFUwRDFIWGFYalN5VHQxeS1FWjBkLVBKYTQ5MFY2LUd6M2FnY1h1bz",
      "publishedAt": "2026-06-12T12:24:10.000Z",
      "source": {
        "name": "Google News"
      },
      "urlToImage": null
    },
    {
      "title": "India vs Pakistan Live Streaming: When and where to watch IND vs PAK Women’s T20 World Cup 2026 match in - The Times of India",
      "url": "https://news.google.com/rss/articles/CBMitAJBVV95cUxNMVdlczdRaGRsS1JGYkdRVVo4UDlyelZOZkpIWWxXZERZWG42SDM2RndlZV9waVUwTEg5a1lCaGJnam50WWRuNWQtUlNzTHVhMzRPLTV6bWRlbjlxNER4M2dQN1FDSlhHZlc2dzdnbHFfelNjSFZKeUF4SjhUaVczVGdHLXJtLWhmNlNiWGRUZzdkcDlTSjVxdzY1bkxWbHRGWk15XzZ6YWRUSHVaLUd5OGFOZi03TnFhZk10ZnVzNGVwNXlPSVVWT090VzBwaUszNHQtSVp3WG0xNzFlRDlONENzd01DTjA1SGU4VEJYamVxcHAzd0taSkpwR202eU1DSUkzN1hwLXVoazN0bHl2OHp3cmtpZVNOR2dIS05BbkxvTnN6VXZBeVA3RFpDSGUtQWNVddIBugJBVV95cUxOaWRoMEpaZDVGMlFpbDlUaTF1OUhkZzd2Y0ZNbzR5SjRWVVpTcXJFQWN1N3lEZGE3d09rTVVwWWpobk54Z21FemRocFdUOFY2YThHUG9qaVVYXy1RbmR2X2JkLURvMF9wdVNPTDJkRllqU1FoUm0wTXBzZlBHb2R0c0trc2psbUhPWFBvVzVDMjN6Ynp1dUo2ZkxhZ2hLdkhoc2xEeXNGai1uNWoyNVdlQVI5V1NDVU5lSGlhNTFjZzhXMlR6X3hRWHpSNjhMa25EYW5kZGY0ZUF6SWlaeU5BdFdJMWh5TkMxS2NxOEVoOUJtWERja0N5dEh4amppSEZ4VUc0TjVtOEJONHcxUXoyVlctRFpsdXB6U3g1bzVQSUIxVzVxN1o0NU5zMlFRQnhsYWhScGlxbnJPUQ?oc=5",
      "description": "<a href=\"https://news.google.com/rss/articles/CBMitAJBVV95cUxNMVdlczdRaGRsS1JGYkdRVVo4UDlyelZOZkpIWWxXZERZWG42SDM2RndlZV9waVUwTEg5a1lCaGJnam50WWRuNWQtUlNzTHVhMzRPLTV6bWRlbjlxNER4M2dQN1FDSlhHZlc2dzdnbHFfelNjSFZKeUF4SjhUaVczVGdHLXJtLWhmNlNiWGRUZzdkcDlTSjVxdzY1bkxWbHRGWk15XzZ6YWRUSHVaLUd5OGFOZi03TnFhZk",
      "publishedAt": "2026-06-13T09:43:00.000Z",
      "source": {
        "name": "Google News"
      },
      "urlToImage": null
    },
    {
      "title": "17 T20 World Cup games, 17 losses - can Ireland break duck? - BBC",
      "url": "https://news.google.com/rss/articles/CBMiZkFVX3lxTE5DaDVrdEtIRFI0ZUV5WTVuX0xBLWdLOHNfb19TQjdQekFTa0VMcm4xUWc1ZDJGZllCY0l2Y0UzT2dzd21OTkJlNlIwR3pjcGdGMDd1TDM3eWJaY2lJa3FzeVVKXzdQdw?oc=5",
      "description": "<a href=\"https://news.google.com/rss/articles/CBMiZkFVX3lxTE5DaDVrdEtIRFI0ZUV5WTVuX0xBLWdLOHNfb19TQjdQekFTa0VMcm4xUWc1ZDJGZllCY0l2Y0UzT2dzd21OTkJlNlIwR3pjcGdGMDd1TDM3eWJaY2lJa3FzeVVKXzdQdw?oc=5\" target=\"_blank\">17 T20 World Cup games, 17 losses - can Ireland break duck?</a>&nbsp;&nbsp;<font color=\"#",
      "publishedAt": "2026-06-12T06:44:56.000Z",
      "source": {
        "name": "Google News"
      },
      "urlToImage": null
    },
    {
      "title": "It's Australia vs South Africa, but not as you know it - ESPNcricinfo",
      "url": "https://news.google.com/rss/articles/CBMiuAFBVV95cUxPV1pEXzNqVnpTeW9XYWhPRW16Snl1QVhyN1h4WHFqdU1nQVNhbEtNZU9XVzhMbm5OUXJadUFqNHd0eWJzc0tzbUlTbklCbFVxbEI1cE9UTDJBOHRhNUxyXzVfenZqblB1NkpWeUtNTkVvRXdTRXhhRUJ5blIwYmNPV0xUR3oyaXN2a01hRmx1blVDMFhILWlqN1JCQXFOMTN5dVp6RW5RVGwybV9VRWRHSzk4RHVReWt20gHKAUFVX3lxTFB4QVNRQ1l5LUtLazRGWGEtOU0tZEVmeGkyclNHZ0ZneUJLYkxZT2wzSW1CTnFXeDNYQzZ0QmNodG9JMHZQWlVLMzF4dkVva05Ld09WS2VmRWk5MGZPMzlHc0lld1AxNFJZNzFvYjViN24zVlcwTlJIODY4NFVjWXlmSm5iaEw2MnNyWkc2NkhpMjVpbGE3QWpFcmlYTld4bUlESk1UeTIzM0pCaGNzNmVRWnppQ1RlYnMyeDdOcUxrU2hKNmtHTHpXR3c?oc=5",
      "description": "<a href=\"https://news.google.com/rss/articles/CBMiuAFBVV95cUxPV1pEXzNqVnpTeW9XYWhPRW16Snl1QVhyN1h4WHFqdU1nQVNhbEtNZU9XVzhMbm5OUXJadUFqNHd0eWJzc0tzbUlTbklCbFVxbEI1cE9UTDJBOHRhNUxyXzVfenZqblB1NkpWeUtNTkVvRXdTRXhhRUJ5blIwYmNPV0xUR3oyaXN2a01hRmx1blVDMFhILWlqN1JCQXFOMTN5dVp6RW5RVGwybV9VRWRHSzk4RHVReWt20g",
      "publishedAt": "2026-06-12T15:35:00.000Z",
      "source": {
        "name": "Google News"
      },
      "urlToImage": null
    },
    {
      "title": "Ready, steady, and unafraid: Netherlands and Scotland aren't just making up the numbers - ESPNcricinfo",
      "url": "https://news.google.com/rss/articles/CBMixwFBVV95cUxNTUxLeXJxcU5JNE5WZk5VWHRPUFBwaFF3Y1BGajBMSzBGc3hvMWVtdVkwa3Jwb0VKTGtReHkzY0tTVjRPWDlORXozd3hzdWtBWGFZUUVMRUM4WXhzUTd2NTdpc3EzY01zZ2JTVTl1M2RCVUZ0djVmN2V2aVVkVzZDbzFZMVJUWm91NFIzWFNjQVZSbWxiSFFWODZlN3I1WTlmdjdzcFJvOXgzLXA2Nk1UbWl2S1FNM04yM3Q5SEItR24yN1NXZW5B0gHYAUFVX3lxTE8yTkhfYVAwakJ2OGUzcTE4NG40WWVzMjRQMW1HZjBXWl9FZmZhTndtdVhINXlZNWdQOUtEdE9pTWc5NUROT3JiMnN6TGY2ZzRsQlJDek9GQzl5M1RIal9CVVpqbHRqUTJVeUIzUWdCVkdITThiVjVGTDZ3Sl9mdnRQVUREa0Z5Z0xLY0I3cnB6cGtOZWhGclVrUDNTaDJfR0tCa0Y3WkZ1WFhHT1lnamNZTmV3OHd6cXc2T3VYSkNIV3JPWXN6YVc4YUQzVjdmblhoZ3dJZC1uOQ?oc=5",
      "description": "<a href=\"https://news.google.com/rss/articles/CBMixwFBVV95cUxNTUxLeXJxcU5JNE5WZk5VWHRPUFBwaFF3Y1BGajBMSzBGc3hvMWVtdVkwa3Jwb0VKTGtReHkzY0tTVjRPWDlORXozd3hzdWtBWGFZUUVMRUM4WXhzUTd2NTdpc3EzY01zZ2JTVTl1M2RCVUZ0djVmN2V2aVVkVzZDbzFZMVJUWm91NFIzWFNjQVZSbWxiSFFWODZlN3I1WTlmdjdzcFJvOXgzLXA2Nk1UbWl2S1FNM04yM3",
      "publishedAt": "2026-06-12T01:39:00.000Z",
      "source": {
        "name": "Google News"
      },
      "urlToImage": null
    },
    {
      "title": "‘Best and most effective way’: Cricket Australia boss triples down on BBL sell-off - SMH.com.au",
      "url": "https://news.google.com/rss/articles/CBMi0wFBVV95cUxPZ25GS3B1cDRhV2Zkc1ZqU3pZaGtNM3VDVEJrZHBySnZ2a01YMFp0cG9rVHktNS1sU1VnQUV1NE1HdkI3dDJVQkRkeU5kaUJZOTFUVVB0cXUySXlLeFppelVUR2lkbXJXY1VDeDlhR1J5cWYyeU40YjZVN3pzaWJSTFZlRTdyUHEwVnJPRW10QzF3VlRwVWQ0anI3WHE0MXgtWkxDR0xNVndWX1JtRkVjUEduZEFZSTdwODZpaGdDUXppQnJzb244Z0lJbkN1NnF3THR3?oc=5",
      "description": "<a href=\"https://news.google.com/rss/articles/CBMi0wFBVV95cUxPZ25GS3B1cDRhV2Zkc1ZqU3pZaGtNM3VDVEJrZHBySnZ2a01YMFp0cG9rVHktNS1sU1VnQUV1NE1HdkI3dDJVQkRkeU5kaUJZOTFUVVB0cXUySXlLeFppelVUR2lkbXJXY1VDeDlhR1J5cWYyeU40YjZVN3pzaWJSTFZlRTdyUHEwVnJPRW10QzF3VlRwVWQ0anI3WHE0MXgtWkxDR0xNVndWX1JtRkVjUEduZEFZSTdwOD",
      "publishedAt": "2026-06-09T09:36:58.000Z",
      "source": {
        "name": "Google News"
      },
      "urlToImage": null
    },
    {
      "title": "SA20 Has Given Cricket Back To The Country: Dale Steyn - NDTV Sports",
      "url": "https://news.google.com/rss/articles/CBMimgFBVV95cUxObllKN085bXZmT1JHNEJCZnAwcjVmRDhBNnQzU19MNUh5YVdIdnhPYU1fajRrcHlkaktyR1lza3BXOWFYMmt6N2RVNWlHUlFidHI1LUVqWlJMQUlIRkQ5Y0o4bW9TQU82c2k5N0dRbmFOQUdPQ1ZGRjByeThJaU9aWTh5ei16STBIeXF5bE52MDNrRzVydmt0Tzdn?oc=5",
      "description": "<a href=\"https://news.google.com/rss/articles/CBMimgFBVV95cUxObllKN085bXZmT1JHNEJCZnAwcjVmRDhBNnQzU19MNUh5YVdIdnhPYU1fajRrcHlkaktyR1lza3BXOWFYMmt6N2RVNWlHUlFidHI1LUVqWlJMQUlIRkQ5Y0o4bW9TQU82c2k5N0dRbmFOQUdPQ1ZGRjByeThJaU9aWTh5ei16STBIeXF5bE52MDNrRzVydmt0Tzdn?oc=5\" target=\"_blank\">SA20 Has Given Cric",
      "publishedAt": "2026-06-12T09:15:36.000Z",
      "source": {
        "name": "Google News"
      },
      "urlToImage": null
    },
    {
      "title": "Gautam Gambhir Urged To Find Hardik Pandya's Backup But Rohit Sharma, Virat Kohli Key - NDTV Sports",
      "url": "https://news.google.com/rss/articles/CBMiwgFBVV95cUxOV2w0dVlWS3VCaFNrcGk4aFRkZktWQUlTUlBPWDJFWklDdHlhcE5RLU9NcnFDNnZDVDdNdkhWbDliVlhjVHp1MEtWekRZR1FwRy1WME9Xc2sxdmZJYjJ2QktVNUgtcWtKZVYxdDlmdDdYdkliNHVUOGVtMVlxSTlfeDNaTW83M1hVODB3YmVwRUR2UkpSWklpbXI2RFFZT0MyQmllMXBfZElsYnd2ejhDNzFNb0hVMUdsTEdYaHZYNXI1UQ?oc=5",
      "description": "<a href=\"https://news.google.com/rss/articles/CBMiwgFBVV95cUxOV2w0dVlWS3VCaFNrcGk4aFRkZktWQUlTUlBPWDJFWklDdHlhcE5RLU9NcnFDNnZDVDdNdkhWbDliVlhjVHp1MEtWekRZR1FwRy1WME9Xc2sxdmZJYjJ2QktVNUgtcWtKZVYxdDlmdDdYdkliNHVUOGVtMVlxSTlfeDNaTW83M1hVODB3YmVwRUR2UkpSWklpbXI2RFFZT0MyQmllMXBfZElsYnd2ejhDNzFNb0hVMUdsTE",
      "publishedAt": "2026-06-11T15:33:49.000Z",
      "source": {
        "name": "Google News"
      },
      "urlToImage": null
    },
    {
      "title": "ICC Finalises Dates For ODI World Cup 2027. Virat Kohli, Rohit Sharma's Timeline Clear: Report - NDTV Sports",
      "url": "https://news.google.com/rss/articles/CBMiywFBVV95cUxQcFhQdVJZLUFQRUhFdHhndUZjZmgtVERjTTV0OWtmZEFHSV9LVHowbW1EekVjSk5DbTBQSG9zQzVSa2lLbC1GNlBtNzMwQ0czbXg1cVlydXdoSHBYQnJsbmw3dmEyTmZtQzJ6Q0lJUzZXNjdwdjl1S3U0Y29GcTBhTV90c1pheFpjNTB1MkRQUFBpM0lNcm9ZckZ2Y0FMMkxFZTl5d0lEbFc5eUdOSEFNOWNQMWVZYkh2dXgtSjNKTVNseEZxazRDWnI5dw?oc=5",
      "description": "<a href=\"https://news.google.com/rss/articles/CBMiywFBVV95cUxQcFhQdVJZLUFQRUhFdHhndUZjZmgtVERjTTV0OWtmZEFHSV9LVHowbW1EekVjSk5DbTBQSG9zQzVSa2lLbC1GNlBtNzMwQ0czbXg1cVlydXdoSHBYQnJsbmw3dmEyTmZtQzJ6Q0lJUzZXNjdwdjl1S3U0Y29GcTBhTV90c1pheFpjNTB1MkRQUFBpM0lNcm9ZckZ2Y0FMMkxFZTl5d0lEbFc5eUdOSEFNOWNQMWVZYkh2dX",
      "publishedAt": "2026-06-12T07:20:20.000Z",
      "source": {
        "name": "Google News"
      },
      "urlToImage": null
    },
    {
      "title": "No Babar Azam, Shaheen Afridi as Pakistan name squad for Asian Games 2026 - The Times of India",
      "url": "https://news.google.com/rss/articles/CBMi6gFBVV95cUxNay1ILWt1ai00bXpyb2loRWlZQ2NLc2kwZVh3Sl94dTR1WlZFM2FJYmJpMVVrSVdiZDBhS0xnSXg4XzdNNWNGcEw2ck9jQy04bzV2MS1QT1pOcFQzUV9QMHV4dFhDenV6Rl9GcmVzNzZoLVpFNGI1cFBpWlRLU0NDMlRFTWo2cUphZzJ2NkxOaEgzMjFJOUhJdGp6d0xoMEVONlBPWUZhZnQ1M3BnUklyLVQwWDlPMm5aRXU2S1huRGd3ZWF1eV9HOFp0Q09FejdYYS1FdzVpWlE2WXFES3luM2NpQ0pDV2kwM0HSAe8BQVVfeXFMTm9ZcmRZaEFhOWVIaVh5WkJVZ2stMktlai1ZMk1zRV9BNWF0VjZMeEc2TVM1NXFjYWVyeTJIYXl0d0JETFdGRllZQkxyU1RyR2FVblBzUkZyTk9xQkZLYlYzRjlBSWxmajMtTGdBM0FSd05rb0dNZ1UzdEdDb2Jlc3hDR2Z2Vk1lamsySnlHQVEyZ002SUNENVlyNk9VTG5Yb0dneGVGRG1EbWlqZDFVWXZkVldhQzgxODJGNDhRR0RDVHcwNkJZSzVCc3Q2YjJuQXFSYmRiRkVyM3AyckJRQzRGODhBREVPR3RCMG8wZHc?oc=5",
      "description": "<a href=\"https://news.google.com/rss/articles/CBMi6gFBVV95cUxNay1ILWt1ai00bXpyb2loRWlZQ2NLc2kwZVh3Sl94dTR1WlZFM2FJYmJpMVVrSVdiZDBhS0xnSXg4XzdNNWNGcEw2ck9jQy04bzV2MS1QT1pOcFQzUV9QMHV4dFhDenV6Rl9GcmVzNzZoLVpFNGI1cFBpWlRLU0NDMlRFTWo2cUphZzJ2NkxOaEgzMjFJOUhJdGp6d0xoMEVONlBPWUZhZnQ1M3BnUklyLVQwWDlPMm5aRX",
      "publishedAt": "2026-06-10T05:11:00.000Z",
      "source": {
        "name": "Google News"
      },
      "urlToImage": null
    },
    {
      "title": "Ben Stokes: England cricket may consider alcohol ban after nightclub incident, says Rob Key - BBC",
      "url": "https://news.google.com/rss/articles/CBMiZkFVX3lxTFAwQTVkMEo0eEJTejJwMDRxdmo0V1RuNllYeUxQemlibFhPVGZJLVRlUjhkZ19IR1VHY0xnZ0FNYXNhY0hnbFRYUzlTWU5WM29rZ0g0Nzg1WnRLRlNJZkZ4Zld5VFo5UQ?oc=5",
      "description": "<ol><li><a href=\"https://news.google.com/rss/articles/CBMiZkFVX3lxTFAwQTVkMEo0eEJTejJwMDRxdmo0V1RuNllYeUxQemlibFhPVGZJLVRlUjhkZ19IR1VHY0xnZ0FNYXNhY0hnbFRYUzlTWU5WM29rZ0g0Nzg1WnRLRlNJZkZ4Zld5VFo5UQ?oc=5\" target=\"_blank\">Ben Stokes: England cricket may consider alcohol ban after nightclub incident, sa",
      "publishedAt": "2026-06-11T13:00:03.000Z",
      "source": {
        "name": "Google News"
      },
      "urlToImage": null
    },
    {
      "title": "Stokes and Atkinson dropped by England for second test against New Zealand while under investigation - AP News",
      "url": "https://news.google.com/rss/articles/CBMilgFBVV95cUxQYUlncVdic3JYMWNKd1U3bkkxSVBKT09NLXE4Umt4c1J0Nk8tNHZUc2tlTzgxZ3ZHRkJRV1lLRHRDYzQyOWowYTFKMUM4LWlMYm8wWGk1dm4yWFFTU1oxcV9OcjhaS3NXald0enFlTXIzcGNFTnYzYm53Q1ZsMVNHd1FlVGd1WndrTmtxN1JoTUp0S0tVWWc?oc=5",
      "description": "<a href=\"https://news.google.com/rss/articles/CBMilgFBVV95cUxQYUlncVdic3JYMWNKd1U3bkkxSVBKT09NLXE4Umt4c1J0Nk8tNHZUc2tlTzgxZ3ZHRkJRV1lLRHRDYzQyOWowYTFKMUM4LWlMYm8wWGk1dm4yWFFTU1oxcV9OcjhaS3NXald0enFlTXIzcGNFTnYzYm53Q1ZsMVNHd1FlVGd1WndrTmtxN1JoTUp0S0tVWWc?oc=5\" target=\"_blank\">Stokes and Atkinson drop",
      "publishedAt": "2026-06-10T15:30:00.000Z",
      "source": {
        "name": "Google News"
      },
      "urlToImage": null
    },
    {
      "title": "Ben Stokes out of England squad, Joe Root captains for second Test - BBC",
      "url": "https://news.google.com/rss/articles/CBMiZkFVX3lxTFBzUE9SenFHdEFBbXlqeGVmOFJSZEZJSWNXZFFaRm1tSHY1NWFvSVhIaVNPemtvLW5SekZYcXVxakdhcENYeEhLbi05QmgzNmpnWGFDdURNV0xQM1ZpZkpPeEFaWW5HQQ?oc=5",
      "description": "<a href=\"https://news.google.com/rss/articles/CBMiZkFVX3lxTFBzUE9SenFHdEFBbXlqeGVmOFJSZEZJSWNXZFFaRm1tSHY1NWFvSVhIaVNPemtvLW5SekZYcXVxakdhcENYeEhLbi05QmgzNmpnWGFDdURNV0xQM1ZpZkpPeEFaWW5HQQ?oc=5\" target=\"_blank\">Ben Stokes out of England squad, Joe Root captains for second Test</a>&nbsp;&nbsp;<font c",
      "publishedAt": "2026-06-10T14:03:22.000Z",
      "source": {
        "name": "Google News"
      },
      "urlToImage": null
    },
    {
      "title": "England’s Bazball reset begins with 115-run win over New Zealand early on Day 4 at Lord’s - AP News",
      "url": "https://news.google.com/rss/articles/CBMipAFBVV95cUxPMHVrVnN2ZFJYRDlKdm4wMUR6WHZPb2RFVWlnV1RzS1ZYWTQtNmxyZWFLVS14ZWRVTE5mVGZrTlhjY3Q2emFmZGdBWjhuN1FzbkdJUm9BQUxhUU1nNUNUUG92X3YwZE5aZmxVSHdVeFIxZmtlWTRmOVQtazhmdDJFLXZuRWZma3E0eE1WdGY5djJFVGJXU0F6cUtlY2wya2tDYlZlOQ?oc=5",
      "description": "<a href=\"https://news.google.com/rss/articles/CBMipAFBVV95cUxPMHVrVnN2ZFJYRDlKdm4wMUR6WHZPb2RFVWlnV1RzS1ZYWTQtNmxyZWFLVS14ZWRVTE5mVGZrTlhjY3Q2emFmZGdBWjhuN1FzbkdJUm9BQUxhUU1nNUNUUG92X3YwZE5aZmxVSHdVeFIxZmtlWTRmOVQtazhmdDJFLXZuRWZma3E0eE1WdGY5djJFVGJXU0F6cUtlY2wya2tDYlZlOQ?oc=5\" target=\"_blank\">Engla",
      "publishedAt": "2026-06-07T13:07:00.000Z",
      "source": {
        "name": "Google News"
      },
      "urlToImage": null
    },
    {
      "title": "Ben Stokes & Gus Atkinson: England cricket need to take accountability - Jonathan Agnew - BBC",
      "url": "https://news.google.com/rss/articles/CBMiZkFVX3lxTE01S05uRTk0V0w2X3ZhSl94dGI0all4NG9RMjB3Q2txX0Q5NFpDRnN3bkVqTHBrYUxaaHB5NkRkeWlJNjdiOUVVbHV5cmhKaHRWazVSUEZRWS1kTFhSZjJXQWdrdUU2UQ?oc=5",
      "description": "<a href=\"https://news.google.com/rss/articles/CBMiZkFVX3lxTE01S05uRTk0V0w2X3ZhSl94dGI0all4NG9RMjB3Q2txX0Q5NFpDRnN3bkVqTHBrYUxaaHB5NkRkeWlJNjdiOUVVbHV5cmhKaHRWazVSUEZRWS1kTFhSZjJXQWdrdUU2UQ?oc=5\" target=\"_blank\">Ben Stokes & Gus Atkinson: England cricket need to take accountability - Jonathan Agnew</",
      "publishedAt": "2026-06-09T16:28:53.000Z",
      "source": {
        "name": "Google News"
      },
      "urlToImage": null
    },
    {
      "title": "Ben Stokes: Could this be the end for England cricket captain? - BBC",
      "url": "https://news.google.com/rss/articles/CBMiZkFVX3lxTE9obGFjWkdtdUlkSElVYWdsZTVyUl83Y0RzWjZtWE1tdXpmaFlsMW44X3lJdC05OWkxR0lhc203N3l6WDlRd280cVk2X3BFM3RYY05wOXFsR2FtTTlBX1hJQ043UVRQQQ?oc=5",
      "description": "<a href=\"https://news.google.com/rss/articles/CBMiZkFVX3lxTE9obGFjWkdtdUlkSElVYWdsZTVyUl83Y0RzWjZtWE1tdXpmaFlsMW44X3lJdC05OWkxR0lhc203N3l6WDlRd280cVk2X3BFM3RYY05wOXFsR2FtTTlBX1hJQ043UVRQQQ?oc=5\" target=\"_blank\">Ben Stokes: Could this be the end for England cricket captain?</a>&nbsp;&nbsp;<font color",
      "publishedAt": "2026-06-09T16:08:43.000Z",
      "source": {
        "name": "Google News"
      },
      "urlToImage": null
    },
    {
      "title": "Dani Wyatt-Hodge, Freya Kemp fuel England's rout in Women's T20 World Cup opener - India Today",
      "url": "https://news.google.com/rss/articles/CBMi5AFBVV95cUxQaU5HYnFHZEtoVUx0TWYzTWVnYXdyUTlFQjdHZHl2ajQ1ZXFFX0Q5LVVkYlhUV1JhRmRIY1NObUNZYTFmLXRuakVUWE8xakRGM2JITGRCanJmTUdIY2RRNXdwUHJDRnI0a005aDE4ajNEYjBBbjQ1eEgxbVprQkZMUnhaeFRZTlhuSVE2MzV4TlpuYVJ0cF9abnpuRFdjMnJCOVJ3dUhMVndfUjJvaUx4ZERFZVZxUzBWcTZOQ19jSlBJWDMtSGFIWTJUbXd3NDBCWWdLY3Q3Z3cxcnd1Y2RwMTA5b1HSAeoBQVVfeXFMT3RvbGFTYnNOQkJjSjBINFNlUnZPRWJCVmVzeGxkTC1uRGRpVTlabVc1TVN5c09wQUlhMzNPdEhfTVV4eGZnUl9TVnRmUlNQelVVcUxaSVpKUmNLUUxVMTBQWkQxVHgxSGFrdUUtTVF6bjd4d251MlZFYnZSTjlBMEtkV0s0aUMtN2ZYMC16NUZmTFlGZUVUWmVDcF9FbmViN3djRVZaZUd2RFdWblgxSE1TaG5xUnlBR2EyWEdoWE9YckxvQnRGTmFtN0FzanZ5dV8xMFlvZjJERTdCZmVmWndGLWxCZHJiaDdR?oc=5",
      "description": "<a href=\"https://news.google.com/rss/articles/CBMi5AFBVV95cUxQaU5HYnFHZEtoVUx0TWYzTWVnYXdyUTlFQjdHZHl2ajQ1ZXFFX0Q5LVVkYlhUV1JhRmRIY1NObUNZYTFmLXRuakVUWE8xakRGM2JITGRCanJmTUdIY2RRNXdwUHJDRnI0a005aDE4ajNEYjBBbjQ1eEgxbVprQkZMUnhaeFRZTlhuSVE2MzV4TlpuYVJ0cF9abnpuRFdjMnJCOVJ3dUhMVndfUjJvaUx4ZERFZVZxUzBWcT",
      "publishedAt": "2026-06-12T22:20:22.000Z",
      "source": {
        "name": "Google News"
      },
      "urlToImage": null
    },
    {
      "title": "ICC WOMEN’S T20 WORLD CUP 2026 TO SET NEW BROADCAST BENCHMARK FOR WOMEN’S CRICKET WITH PIONEERING PRODUCTION - ICC",
      "url": "https://news.google.com/rss/articles/CBMi5gFBVV95cUxPQ1BrMThlRTdieW1QdUZGQUFTTmlUNVZPLTA5OFNRaFZoWUU4UU1OWnVwbW5HQzlBMDlvRFFKLVd6NXVYT2hXUVZnemM0YzVxRjlUblVmMjAxSkNxbjBiM193TVZSWS1JNU9QSWNTWE5oUUd0endrM3FaWFE2TmdSZ0tBTFNYXzVvNlk3QWJpRmpWR1dBbGxuTUpUOGxlMGU4UlpkT1RSMWF6SVN4bm9NaVBOQ3I4Qkd4UXQxRGU4YWlobUQ4cV9vOW4xYjBLRmhrak53by15WlB2UVdpY1ZFR0NSZzVwdw?oc=5",
      "description": "<a href=\"https://news.google.com/rss/articles/CBMi5gFBVV95cUxPQ1BrMThlRTdieW1QdUZGQUFTTmlUNVZPLTA5OFNRaFZoWUU4UU1OWnVwbW5HQzlBMDlvRFFKLVd6NXVYT2hXUVZnemM0YzVxRjlUblVmMjAxSkNxbjBiM193TVZSWS1JNU9QSWNTWE5oUUd0endrM3FaWFE2TmdSZ0tBTFNYXzVvNlk3QWJpRmpWR1dBbGxuTUpUOGxlMGU4UlpkT1RSMWF6SVN4bm9NaVBOQ3I4Qkd4UX",
      "publishedAt": "2026-06-11T08:04:12.000Z",
      "source": {
        "name": "Google News"
      },
      "urlToImage": null
    },
    {
      "title": "India vs Afghanistan 1st ODI: Dharamsala weather update, live streaming, squad details - Here's all you need to know | Cricket - Hindustan Times",
      "url": "https://news.google.com/rss/articles/CBMi_wFBVV95cUxPcklFbEhpN2N2TFZ4dFlISWVaa2ZmcGxGUHVnQzF1aEVQV0hCR0JxQVZ6bzVRWXR1N25QZVktSnB3SmtWRFkyTzJ1ZGJjTDBpWWFmZ2xHZzVOOTFkSUhSRXhLR0NQbXZ0WmY2ekZNNk96RVZJZ1UtS3VnemFFbW1nRG5xbXhkVFllUkFRVlJzaHlxTnJLOVYtOUIxMUUySVF0ZHpVcVdSYVFWVk45Q1lva2VDaDBQOVNNVmh3Q00zaU00TlZheDhnZ2h1a1pEQXpTWTAxYXdhRjdWdC1tVTN0R0t0ckw4NXA5Ym4wakFfTGx2WnVYN0MwbUhoQlhPS1nSAYQCQVVfeXFMTlc1MmxLOVNlcndqeXRWYlRfYnVFOXFVS0pMS29OcFJqeGJZcEJzTXdmX05lckxldHJ6QlhkVWYyV1c2Qy1GMjhTVWVxRml3VTdHWFRVNW9XRGEwOWZBemVDRHVBWUVnU3JsajRMWlpwYjk1Nmp1TFo1T2JTYjJadHNhTXhvS3kzQm9YaFZtbTJjaXdiV2F0dWhwMG1McC1xS243dzB3RG1yelN0eWZUS2hpYmFsdmZBRlVjT2lNclhsMEpLRVM4NmNGNlZCbG4tdWs5VU5PYXVKVmtSWUNpTURoRHU4bjFRSlFFc1RueFJMcTN5c3ZCN1VIRTQ5RzlZUzNKRkc?oc=5",
      "description": "<a href=\"https://news.google.com/rss/articles/CBMi_wFBVV95cUxPcklFbEhpN2N2TFZ4dFlISWVaa2ZmcGxGUHVnQzF1aEVQV0hCR0JxQVZ6bzVRWXR1N25QZVktSnB3SmtWRFkyTzJ1ZGJjTDBpWWFmZ2xHZzVOOTFkSUhSRXhLR0NQbXZ0WmY2ekZNNk96RVZJZ1UtS3VnemFFbW1nRG5xbXhkVFllUkFRVlJzaHlxTnJLOVYtOUIxMUUySVF0ZHpVcVdSYVFWVk45Q1lva2VDaDBQOVNNVm",
      "publishedAt": "2026-06-13T04:41:27.000Z",
      "source": {
        "name": "Google News"
      },
      "urlToImage": null
    },
    {
      "title": "Cricket Ireland issues statement amid Belfast unrest ahead of high-profile India T20Is - The Times of India",
      "url": "https://news.google.com/rss/articles/CBMi_AFBVV95cUxPX1lfeGdhSmhrbHptSWJDX05JcEdRTVNLbG9aTkhkOWhLcXZJUEkxWHZUNVVGT01XNGxKZ0duNnk0QTRxSzctem92V0hmcTFDRENIYXBwNXZsdFlGUmZhc21zd0N3R1JvYVlSWFAyZldBZ2hIdS1fMWcwYjhDd1hIX1hWZUkxTlhvclJsdWQtWHNhUXBoRVZMeWxwcE9EUXdwRWFMM25zcWNXVzNKcDhtdHM5MGJTTE9QMmsweHZDOGd1bnd5X1ZHY2t0SGNIRXFkSUFCT2NHaUV0cFY5OF82enVVb0lIcGYyNlFfSnhSRGdtZ1dOYWxQaHAzMEXSAYICQVVfeXFMT2NvemFYUXRrTnoxQjdlZkY4TlQxUXFFYXdjSkQzaElhSU5EVGlRMVY5Z2NXVkhQdVlheXZuYzA1Rm1NMGZsT2FnWDJ6TF9fSFJKaVV1aEs3R3ZkcGd3ZERlRWExYm52eTdlVU1pVEw4eHFlX1AyV1hial9PRUlkTUpITDZMSEZfT2J5OWRGc1UtdFVKZThyWlk5M0dzMzhyTDlRcEhfMzQ0VkhIeFR3VHF6aUI5eDg0V2hXOUNtalA5emp5V0VGYURzV1Q4NHJ2UVluNWtSUmdVQXM3cjliQXRud1dReDZQcFQwWk5HaW1pXzQ4RHFELUlnMGFZTGlNeFJB?oc=5",
      "description": "<a href=\"https://news.google.com/rss/articles/CBMi_AFBVV95cUxPX1lfeGdhSmhrbHptSWJDX05JcEdRTVNLbG9aTkhkOWhLcXZJUEkxWHZUNVVGT01XNGxKZ0duNnk0QTRxSzctem92V0hmcTFDRENIYXBwNXZsdFlGUmZhc21zd0N3R1JvYVlSWFAyZldBZ2hIdS1fMWcwYjhDd1hIX1hWZUkxTlhvclJsdWQtWHNhUXBoRVZMeWxwcE9EUXdwRWFMM25zcWNXVzNKcDhtdHM5MGJTTE9QMm",
      "publishedAt": "2026-06-12T06:19:00.000Z",
      "source": {
        "name": "Google News"
      },
      "urlToImage": null
    }
  ],
  "culture": [
    {
      "title": "Twenty20 cricket | Rules, History, World Cup, 2026, Scores, Matches, Highlights, Rankings, Schedule, & Facts - Britannica",
      "url": "https://news.google.com/rss/articles/CBMiX0FVX3lxTE5Odk91S3pNRGZOaml6OS16elJSRHhxMkxaZ09ERmFveVNnU2FuNmRaSGk4OVZvSGdFb1hveG1DRGZWZi1XQzVxNUdlV08tLXRDS2Q5U1docjJKWHY4b0c4?oc=5",
      "description": "<a href=\"https://news.google.com/rss/articles/CBMiX0FVX3lxTE5Odk91S3pNRGZOaml6OS16elJSRHhxMkxaZ09ERmFveVNnU2FuNmRaSGk4OVZvSGdFb1hveG1DRGZWZi1XQzVxNUdlV08tLXRDS2Q5U1docjJKWHY4b0c4?oc=5\" target=\"_blank\">Twenty20 cricket | Rules, History, World Cup, 2026, Scores, Matches, Highlights, Rankings, Schedule",
      "publishedAt": "2026-06-09T05:00:00.000Z",
      "source": {
        "name": "Google News"
      },
      "urlToImage": null
    },
    {
      "title": "Cricket’s Canadian surge: the top 5 rules every beginner should know - Cricket World",
      "url": "https://news.google.com/rss/articles/CBMiqwFBVV95cUxNS1g0Qkt3MThTSmpreHJ4VHk2aEFQeEZ3UmhvOHFGWkt0NzV6YmxVWjdIb3NaeW1mZEFSdzY2M2VvTVU3am91OHk2R21UVUo5VGZKNnJ1RmhJNXZfUk1xbDRXM3JkaHZZdk1LNW1md1NSSGJiblY1Y0paWmJMekw5T0lVUmF5V2pQcWppYWhHaXRRNXh0VVN4ZUItb0tqdTNxTGxxaGRfdGxtYVE?oc=5",
      "description": "<a href=\"https://news.google.com/rss/articles/CBMiqwFBVV95cUxNS1g0Qkt3MThTSmpreHJ4VHk2aEFQeEZ3UmhvOHFGWkt0NzV6YmxVWjdIb3NaeW1mZEFSdzY2M2VvTVU3am91OHk2R21UVUo5VGZKNnJ1RmhJNXZfUk1xbDRXM3JkaHZZdk1LNW1md1NSSGJiblY1Y0paWmJMekw5T0lVUmF5V2pQcWppYWhHaXRRNXh0VVN4ZUItb0tqdTNxTGxxaGRfdGxtYVE?oc=5\" target=\"_bla",
      "publishedAt": "2026-06-04T07:00:00.000Z",
      "source": {
        "name": "Google News"
      },
      "urlToImage": null
    },
    {
      "title": "Cricket World Cup | Schedule, Matches, Winners, Women’s Edition, & Facts - Britannica",
      "url": "https://news.google.com/rss/articles/CBMiYEFVX3lxTE51MXFtQ0xFbEJ5WFExU1Zqd0hqa3Y4bjZ6d19LdUE2cy03X0VYR3h2NkdXME1MYXFZMW1BRDduZnQ2VTAxOFV3ZG1VMEtNdkRrSzRRUHJMeU5qa2pRd0g4OA?oc=5",
      "description": "<a href=\"https://news.google.com/rss/articles/CBMiYEFVX3lxTE51MXFtQ0xFbEJ5WFExU1Zqd0hqa3Y4bjZ6d19LdUE2cy03X0VYR3h2NkdXME1MYXFZMW1BRDduZnQ2VTAxOFV3ZG1VMEtNdkRrSzRRUHJMeU5qa2pRd0g4OA?oc=5\" target=\"_blank\">Cricket World Cup | Schedule, Matches, Winners, Women’s Edition, & Facts</a>&nbsp;&nbsp;<font col",
      "publishedAt": "2026-05-29T07:00:00.000Z",
      "source": {
        "name": "Google News"
      },
      "urlToImage": null
    },
    {
      "title": "Cricket World Test Championship Explained: Format, Points and Final Qualification - World In Sport",
      "url": "https://news.google.com/rss/articles/CBMidEFVX3lxTFA4Vk85SlhOOG5aY2NfWXR2Zkg5STZKbFMzcFdwaEs0ZnZZUmxhWFhhdnItWEJXeWZralVrNzJEMVNmZURVY2ppZG41Vm5oeFhja1JtY3FhNFRncFVTQ3gzcVptWV8tSnRBMkN3TjZGaUplemtu?oc=5",
      "description": "<a href=\"https://news.google.com/rss/articles/CBMidEFVX3lxTFA4Vk85SlhOOG5aY2NfWXR2Zkg5STZKbFMzcFdwaEs0ZnZZUmxhWFhhdnItWEJXeWZralVrNzJEMVNmZURVY2ppZG41Vm5oeFhja1JtY3FhNFRncFVTQ3gzcVptWV8tSnRBMkN3TjZGaUplemtu?oc=5\" target=\"_blank\">Cricket World Test Championship Explained: Format, Points and Final Qua",
      "publishedAt": "2026-06-11T23:34:55.000Z",
      "source": {
        "name": "Google News"
      },
      "urlToImage": null
    },
    {
      "title": "Major records that may be broken at Women’s T20 World Cup - ICC",
      "url": "https://news.google.com/rss/articles/CBMivAFBVV95cUxQQ0s3RjVMVElTQVRodmdQZWdlOElrSkxoN1ctcHZpTUpwUF9QRHo2QTZkdFZUaDBXS3J3NEZsMHdEeG1tTTRCM3piRDl3LUN6Y2doTkhPekVMTWtyMmVaRGxteWVwenZmLXlETTZmeEJsVkxJZGljMUxJQmFXQWhNYkNHelNuOFNockpPclBhRlBQWUd5NGs2NG1LZWlvS29GREZ4Mnh0TkR2b1BmajBxQUVqUThYSEZNNHdpTQ?oc=5",
      "description": "<a href=\"https://news.google.com/rss/articles/CBMivAFBVV95cUxQQ0s3RjVMVElTQVRodmdQZWdlOElrSkxoN1ctcHZpTUpwUF9QRHo2QTZkdFZUaDBXS3J3NEZsMHdEeG1tTTRCM3piRDl3LUN6Y2doTkhPekVMTWtyMmVaRGxteWVwenZmLXlETTZmeEJsVkxJZGljMUxJQmFXQWhNYkNHelNuOFNockpPclBhRlBQWUd5NGs2NG1LZWlvS29GREZ4Mnh0TkR2b1BmajBxQUVqUThYSEZNNH",
      "publishedAt": "2026-06-04T07:00:00.000Z",
      "source": {
        "name": "Google News"
      },
      "urlToImage": null
    },
    {
      "title": "IPL 2026 RECORD ALERT: Kohli, Klaasen, Sooryavanshi and Sudharsan in century race - supersport.com",
      "url": "https://news.google.com/rss/articles/CBMi5gFBVV95cUxQdlZIMm54U1gyN0ZHc3hUSmlHV0VfY1BvSEh0QURLTXJIWEw4cEpDNWloZnNRQlBLVkZQUEc5bnFmYlczanp1a3Q2ZEpIQnNoMU05bld4WFNjM3g5RGM0ZWpJQjhYTXZhN3ZYWks1SGFOdTNFbmhseWpxUnMwb0ptWmRQSU5ZajhTWW9jU2VFZl93MkZQV3JYTTI1ZG9xSEFyWncwb2JBOFQ1WU94bEdHMWdScHlxa09uZWt1bGNUZ09mb05NejRYR1lYMWlKSnk5THd0YmxkWmFPT08yUlJYMTRfUHFkdw?oc=5",
      "description": "<a href=\"https://news.google.com/rss/articles/CBMi5gFBVV95cUxQdlZIMm54U1gyN0ZHc3hUSmlHV0VfY1BvSEh0QURLTXJIWEw4cEpDNWloZnNRQlBLVkZQUEc5bnFmYlczanp1a3Q2ZEpIQnNoMU05bld4WFNjM3g5RGM0ZWpJQjhYTXZhN3ZYWks1SGFOdTNFbmhseWpxUnMwb0ptWmRQSU5ZajhTWW9jU2VFZl93MkZQV3JYTTI1ZG9xSEFyWncwb2JBOFQ1WU94bEdHMWdScHlxa09uZW",
      "publishedAt": "2026-05-26T07:00:00.000Z",
      "source": {
        "name": "Google News"
      },
      "urlToImage": null
    },
    {
      "title": "'Ek Bihari, sab pe bhari': After a record-breaking IPL season, Vaibhav Sooryavanshi gets his India moment - The Times of India",
      "url": "https://news.google.com/rss/articles/CBMijwJBVV95cUxNeFNxdkVaV3hqcUZtajU4ZHB3U2o1X09taE9wLVRWcUJNcWYtcEp6UENhR0JBeDZDOU16MEFrbDdhTVN2UWJ0MFZzTFV2QnFnb1E3VHc2eS1DYXA4bFJlZW56N1FrUkFJY0o0dnlpMmJmblo0OXVFM2NVYXRma1lYQTVMNUZvUFg2aXNlVHRudW5rQ21XN24xU1ZqYTVuSGJ3clZkNnBsSmpZOHBfa1FHdnpCeV9MR2Z4TjlvOTAySmVsTTdXajctUzhFUWhnUGdnY3VwQV94NXFwSEkyWjNUT2MyNzh2TzVhdnd2TVdscndwSV94UkpucUxIaUs4Q0ZkVU9DNktZSDNUUTVzem5Z?oc=5",
      "description": "<a href=\"https://news.google.com/rss/articles/CBMijwJBVV95cUxNeFNxdkVaV3hqcUZtajU4ZHB3U2o1X09taE9wLVRWcUJNcWYtcEp6UENhR0JBeDZDOU16MEFrbDdhTVN2UWJ0MFZzTFV2QnFnb1E3VHc2eS1DYXA4bFJlZW56N1FrUkFJY0o0dnlpMmJmblo0OXVFM2NVYXRma1lYQTVMNUZvUFg2aXNlVHRudW5rQ21XN24xU1ZqYTVuSGJ3clZkNnBsSmpZOHBfa1FHdnpCeV9MR2Z4Tj",
      "publishedAt": "2026-06-06T07:45:00.000Z",
      "source": {
        "name": "Google News"
      },
      "urlToImage": null
    },
    {
      "title": "Five Record-Breaking Moments And Stats From IPL That Still Remain Iconic - ABP News",
      "url": "https://news.google.com/rss/articles/CBMivAFBVV95cUxPUjdiN09FcHlFWUctc0VEd25fVDNyZDJUWkN5ZGFvQlRnQUZQZk1JZTZZOTBmRGlnOG5VVWZxQ0lGcGpMeGJ6V01NLUVCUDNNX2drMHYtb0x4UGNyaWdzY2ZzS09JclhjWDJBR2pUNTk2VWlsS000elA4ZW00OUJEU1A1SHJmdE5RLW1iTlFsS3p3eU9zM2ZhRGlfUWI4WFBDRGlOZnFxR05rT0FkSnN1RF81UE9RWFpQeW9ETtIBwgFBVV95cUxQWFA4ektQTnMzVG5PT25nZlM2RDBkd2ZjR3dfODlBbW84bzNyLUJUMmczQy1OalhjS0tFOHZrbVFGTU0xN0xXeW84RWZ0OGFYZ3FnbGJvc3Bldng3NHpGdHpTSm9lSE02SXdaQmlpbU5mYjM4Q3hlTnpZMHY0V0pxbFMxSlN4Q3pOWEtqTlhRaFd5RkxMYkZ3ZlFpUVNPbDNWYnpZSnk0Q2VIM21GYmdrc2RESlNEb0dOdVpZR1MwTWw4UQ?oc=5",
      "description": "<a href=\"https://news.google.com/rss/articles/CBMivAFBVV95cUxPUjdiN09FcHlFWUctc0VEd25fVDNyZDJUWkN5ZGFvQlRnQUZQZk1JZTZZOTBmRGlnOG5VVWZxQ0lGcGpMeGJ6V01NLUVCUDNNX2drMHYtb0x4UGNyaWdzY2ZzS09JclhjWDJBR2pUNTk2VWlsS000elA4ZW00OUJEU1A1SHJmdE5RLW1iTlFsS3p3eU9zM2ZhRGlfUWI4WFBDRGlOZnFxR05rT0FkSnN1RF81UE9RWFpQeW",
      "publishedAt": "2026-05-23T07:00:00.000Z",
      "source": {
        "name": "Google News"
      },
      "urlToImage": null
    },
    {
      "title": "IPL 2026 Biggest Moments, Shocking Exits & Record-Breaking Drama – The Craziest Season in IPL History? - Cric-Mate",
      "url": "https://news.google.com/rss/articles/CBMimwFBVV95cUxNOXlXUDFlalRYLVpuY2E2TzBzdm1pYmlQVVlPSmdtODBQbW5NN0FfVGFDQW1uSmtPdkprOE5LNDhHU1UwYUluNkp6VGtnUi1VZ0g5NGRxalZ0U2U3cVRPblc4djliMExldzBBV0lCOWpiX0g5UThreGo4TlRmWldZUGE4cnlncjItMjZ4alJUM2V2RzZoSnQwVV9INA?oc=5",
      "description": "<a href=\"https://news.google.com/rss/articles/CBMimwFBVV95cUxNOXlXUDFlalRYLVpuY2E2TzBzdm1pYmlQVVlPSmdtODBQbW5NN0FfVGFDQW1uSmtPdkprOE5LNDhHU1UwYUluNkp6VGtnUi1VZ0g5NGRxalZ0U2U3cVRPblc4djliMExldzBBV0lCOWpiX0g5UThreGo4TlRmWldZUGE4cnlncjItMjZ4alJUM2V2RzZoSnQwVV9INA?oc=5\" target=\"_blank\">IPL 2026 Biggest ",
      "publishedAt": "2026-05-26T07:00:00.000Z",
      "source": {
        "name": "Google News"
      },
      "urlToImage": null
    },
    {
      "title": "IPL 2026 stats and records: Biggest runs, wickets, sixes and historic moments - MSN",
      "url": "https://news.google.com/rss/articles/CBMixgFBVV95cUxQaGw5eFJCQ1RvWlZmX2loSnFKYnFyYTRkZnhIelg4UHk2WThraVpIOXdJaG5XTDAxdXdSc0J4RGNtUnExUEx1VndWR3JrRzdGS05VREwzbFdTU0V4aVVhUHlMOS1PWkhBZmhyN0dyV29neTlYbzVyZ3pZV01FaXV6N0NSZkg2dzZveWEyVjNnNFZmNTBwTi1yUDVaN2tmWW5SZy1tNEVSNXpZVFpzbWxFRGtyR1lSODNsNi1MdjNLWTM0bnlKM3c?oc=5",
      "description": "<a href=\"https://news.google.com/rss/articles/CBMixgFBVV95cUxQaGw5eFJCQ1RvWlZmX2loSnFKYnFyYTRkZnhIelg4UHk2WThraVpIOXdJaG5XTDAxdXdSc0J4RGNtUnExUEx1VndWR3JrRzdGS05VREwzbFdTU0V4aVVhUHlMOS1PWkhBZmhyN0dyV29neTlYbzVyZ3pZV01FaXV6N0NSZkg2dzZveWEyVjNnNFZmNTBwTi1yUDVaN2tmWW5SZy1tNEVSNXpZVFpzbWxFRGtyR1lSODNsNi",
      "publishedAt": "2026-06-11T18:23:45.000Z",
      "source": {
        "name": "Google News"
      },
      "urlToImage": null
    }
  ],
  "videos": []
}